{
	"Version": 3,
	"Parameters": [
		{
			"Id": "ParamAngleX",
			"GroupId": "ParamGroup5",
			"Name": "角度 X"
		},
		{
			"Id": "ParamAngleY",
			"GroupId": "ParamGroup5",
			"Name": "角度 Y"
		},
		{
			"Id": "ParamAngleZ",
			"GroupId": "ParamGroup5",
			"Name": "角度 Z"
		},
		{
			"Id": "ParamCheek",
			"GroupId": "ParamGroup5",
			"Name": "[spe]脸颊泛红"
		},
		{
			"Id": "Param",
			"GroupId": "ParamGroup5",
			"Name": "[spe]眼部替换"
		},
		{
			"Id": "ParamBodyAngleX",
			"GroupId": "ParamGroup6",
			"Name": "身体旋转　X"
		},
		{
			"Id": "ParamBodyAngleY",
			"GroupId": "ParamGroup6",
			"Name": "身体旋转　Y"
		},
		{
			"Id": "ParamBodyAngleZ",
			"GroupId": "ParamGroup6",
			"Name": "身体旋转　Z"
		},
		{
			"Id": "ParamBreath",
			"GroupId": "ParamGroup6",
			"Name": "呼吸"
		},
		{
			"Id": "ParamEyeBallX",
			"GroupId": "ParamGroup",
			"Name": "眼珠 X"
		},
		{
			"Id": "ParamEyeBallY",
			"GroupId": "ParamGroup",
			"Name": "眼珠 Y"
		},
		{
			"Id": "ParamEyeBallFormL",
			"GroupId": "ParamGroup",
			"Name": "[phy]左眼珠收缩"
		},
		{
			"Id": "ParamEyeBallFormR",
			"GroupId": "ParamGroup",
			"Name": "[phy]右眼珠收缩"
		},
		{
			"Id": "ParameyespinL",
			"GroupId": "ParamGroup",
			"Name": "[phy]左眼流转"
		},
		{
			"Id": "ParameyespinR",
			"GroupId": "ParamGroup",
			"Name": "[phy]右眼流转"
		},
		{
			"Id": "ParamlightcontraL",
			"GroupId": "ParamGroup",
			"Name": "[phy]左眼高光收缩"
		},
		{
			"Id": "ParamlightcontraR",
			"GroupId": "ParamGroup",
			"Name": "[phy]右眼高光收缩"
		},
		{
			"Id": "ParamEyeLOpen",
			"GroupId": "ParamGroup2",
			"Name": "[mix]左眼开闭"
		},
		{
			"Id": "ParamEyeROpen",
			"GroupId": "ParamGroup2",
			"Name": "[mix]右眼开闭"
		},
		{
			"Id": "ParamEyeLSmile",
			"GroupId": "ParamGroup2",
			"Name": "[mix][smile]左眼微笑"
		},
		{
			"Id": "ParamEyeRSmile",
			"GroupId": "ParamGroup2",
			"Name": "[mix][smile]右眼微笑"
		},
		{
			"Id": "ParamEyeLForm",
			"GroupId": "ParamGroup2",
			"Name": "[mix][smile]左眼变形"
		},
		{
			"Id": "ParamEyeRForm",
			"GroupId": "ParamGroup2",
			"Name": "[mix][smile]右眼变形"
		},
		{
			"Id": "ParamMouthForm",
			"GroupId": "ParamGroup3",
			"Name": "[smile][mix]嘴笑容"
		},
		{
			"Id": "ParamMouthOpen",
			"GroupId": "ParamGroup3",
			"Name": "[mix]嘴张开和闭合"
		},
		{
			"Id": "ParamMouthA",
			"GroupId": "ParamGroup3",
			"Name": "[mix]A"
		},
		{
			"Id": "ParamMouthI",
			"GroupId": "ParamGroup3",
			"Name": "[mix]I"
		},
		{
			"Id": "ParamMouthU",
			"GroupId": "ParamGroup3",
			"Name": "[mix]U"
		},
		{
			"Id": "ParamMouthE",
			"GroupId": "ParamGroup3",
			"Name": "[mix]E"
		},
		{
			"Id": "ParamMouthO",
			"GroupId": "ParamGroup3",
			"Name": "[mix]O"
		},
		{
			"Id": "ParamBrowLY",
			"GroupId": "ParamGroup4",
			"Name": "左眉上下"
		},
		{
			"Id": "ParamBrowLX",
			"GroupId": "ParamGroup4",
			"Name": "左眉左右"
		},
		{
			"Id": "ParamBrowLAngle",
			"GroupId": "ParamGroup4",
			"Name": "[open][mix]左眉角度"
		},
		{
			"Id": "ParamBrowLForm",
			"GroupId": "ParamGroup4",
			"Name": "[smile][mix]左眉変形"
		},
		{
			"Id": "ParamBrowRY",
			"GroupId": "ParamGroup4",
			"Name": "右眉上下"
		},
		{
			"Id": "ParamBrowRX",
			"GroupId": "ParamGroup4",
			"Name": "右眉左右"
		},
		{
			"Id": "ParamBrowRAngle",
			"GroupId": "ParamGroup4",
			"Name": "[open][mix]右眉角度"
		},
		{
			"Id": "ParamBrowRForm",
			"GroupId": "ParamGroup4",
			"Name": "[smile][mix]右眉変形"
		},
		{
			"Id": "ParamarmspinL",
			"GroupId": "ParamGroup91",
			"Name": "左大臂旋转"
		},
		{
			"Id": "ParamforearmspinL",
			"GroupId": "ParamGroup91",
			"Name": "左小臂旋转"
		},
		{
			"Id": "ParamarmspinR",
			"GroupId": "ParamGroup91",
			"Name": "右大臂旋转"
		},
		{
			"Id": "ParamforearmspinR",
			"GroupId": "ParamGroup91",
			"Name": "右小臂旋转"
		},
		{
			"Id": "Paramwaveback",
			"GroupId": "ParamGroup14",
			"Name": "颈饰摇动"
		},
		{
			"Id": "Paramwavedrop",
			"GroupId": "ParamGroup14",
			"Name": "挂坠摇动"
		},
		{
			"Id": "Paramwavebeast",
			"GroupId": "ParamGroup14",
			"Name": "胸部衣服摇动"
		},
		{
			"Id": "Paramdresswave",
			"GroupId": "ParamGroup14",
			"Name": "裙袍摇动"
		},
		{
			"Id": "Paramhairclaspware",
			"GroupId": "ParamGroup14",
			"Name": "发箍百褶摇动"
		},
		{
			"Id": "Paramdressflu",
			"GroupId": "ParamGroup7",
			"Name": "裙袍蓬松"
		},
		{
			"Id": "Paramflubeast",
			"GroupId": "ParamGroup7",
			"Name": "胸部衣物蓬松"
		},
		{
			"Id": "Rbowtideflu",
			"GroupId": "ParamGroup7",
			"Name": "右蝴蝶结蓬松"
		},
		{
			"Id": "Lbowtideflu",
			"GroupId": "ParamGroup7",
			"Name": "左蝴蝶结蓬松"
		},
		{
			"Id": "Parambowblack1flu",
			"GroupId": "ParamGroup7",
			"Name": "发饰蝴蝶结黑_1蓬松"
		},
		{
			"Id": "Parambowblack2flu",
			"GroupId": "ParamGroup7",
			"Name": "发饰蝴蝶结黑_2蓬松"
		},
		{
			"Id": "Parambowblack3flu",
			"GroupId": "ParamGroup7",
			"Name": "发饰蝴蝶结黑_3蓬松"
		},
		{
			"Id": "Parambowblack4flu",
			"GroupId": "ParamGroup7",
			"Name": "发饰蝴蝶结黑_4蓬松"
		},
		{
			"Id": "Parambowblue1flu",
			"GroupId": "ParamGroup7",
			"Name": "发饰蝴蝶结蓝_1蓬松"
		},
		{
			"Id": "Parambowblue2flu",
			"GroupId": "ParamGroup7",
			"Name": "发饰蝴蝶结蓝_2蓬松"
		},
		{
			"Id": "Parambowblue3flu",
			"GroupId": "ParamGroup7",
			"Name": "发饰蝴蝶结蓝_3蓬松"
		},
		{
			"Id": "Parambowblue4flu",
			"GroupId": "ParamGroup7",
			"Name": "发饰蝴蝶结蓝_4蓬松"
		},
		{
			"Id": "Parambowgrown1flu",
			"GroupId": "ParamGroup7",
			"Name": "发饰蝴蝶结灰_1蓬松"
		},
		{
			"Id": "Parambowwhite1flu",
			"GroupId": "ParamGroup7",
			"Name": "发饰蝴蝶结白_1蓬松"
		},
		{
			"Id": "Parambowwhite2flu",
			"GroupId": "ParamGroup7",
			"Name": "发饰蝴蝶结白_2蓬松"
		},
		{
			"Id": "Parambeast1flu",
			"GroupId": "ParamGroup7",
			"Name": "胸饰缎带1蓬松"
		},
		{
			"Id": "Parambeast2flu",
			"GroupId": "ParamGroup7",
			"Name": "胸饰缎带2蓬松"
		},
		{
			"Id": "Param1_1flu",
			"GroupId": "ParamGroup7",
			"Name": "头发1_1蓬松"
		},
		{
			"Id": "Param2_1flu",
			"GroupId": "ParamGroup7",
			"Name": "头发2_1蓬松"
		},
		{
			"Id": "Param3_2flu",
			"GroupId": "ParamGroup7",
			"Name": "头发3_2蓬松"
		},
		{
			"Id": "Param2_8flu",
			"GroupId": "ParamGroup7",
			"Name": "头发2_8蓬松"
		},
		{
			"Id": "Param2_2flu",
			"GroupId": "ParamGroup7",
			"Name": "头发2_2蓬松"
		},
		{
			"Id": "Param1_2flu",
			"GroupId": "ParamGroup7",
			"Name": "头发1_2蓬松"
		},
		{
			"Id": "Param5_2flu",
			"GroupId": "ParamGroup7",
			"Name": "头发5_2蓬松"
		},
		{
			"Id": "Param4_2flu",
			"GroupId": "ParamGroup7",
			"Name": "头发4_2蓬松"
		},
		{
			"Id": "Param6_2flu",
			"GroupId": "ParamGroup7",
			"Name": "头发6_2蓬松"
		},
		{
			"Id": "Param7_2flu",
			"GroupId": "ParamGroup7",
			"Name": "头发7_2蓬松"
		},
		{
			"Id": "Param9_2flu",
			"GroupId": "ParamGroup7",
			"Name": "头发9_2蓬松"
		},
		{
			"Id": "Param8_2flu",
			"GroupId": "ParamGroup7",
			"Name": "头发8_2蓬松"
		},
		{
			"Id": "Param11_2flu",
			"GroupId": "ParamGroup7",
			"Name": "头发11_2蓬松"
		},
		{
			"Id": "Param10_2flu",
			"GroupId": "ParamGroup7",
			"Name": "头发10_2蓬松"
		},
		{
			"Id": "Param1_3flu",
			"GroupId": "ParamGroup7",
			"Name": "头发1_3蓬松"
		},
		{
			"Id": "Param2_3flu",
			"GroupId": "ParamGroup7",
			"Name": "头发2_3蓬松"
		},
		{
			"Id": "Param3_3flu",
			"GroupId": "ParamGroup7",
			"Name": "头发3_3蓬松"
		},
		{
			"Id": "Param4_4flu",
			"GroupId": "ParamGroup7",
			"Name": "头发4_4蓬松"
		},
		{
			"Id": "Param1_4flu",
			"GroupId": "ParamGroup7",
			"Name": "头发1_4蓬松"
		},
		{
			"Id": "Param2_4flu",
			"GroupId": "ParamGroup7",
			"Name": "头发2_4蓬松"
		},
		{
			"Id": "Param3_4flu",
			"GroupId": "ParamGroup7",
			"Name": "头发3_4蓬松"
		},
		{
			"Id": "Param_Angle_Rotation_1_ArtMesh87",
			"GroupId": "ParamGroup8",
			"Name": "[0]头发1_1"
		},
		{
			"Id": "Param_Angle_Rotation_2_ArtMesh87",
			"GroupId": "ParamGroup8",
			"Name": "[1]头发1_1"
		},
		{
			"Id": "Param_Angle_Rotation_3_ArtMesh87",
			"GroupId": "ParamGroup8",
			"Name": "[2]头发1_1"
		},
		{
			"Id": "Param_Angle_Rotation_4_ArtMesh87",
			"GroupId": "ParamGroup8",
			"Name": "[3]头发1_1"
		},
		{
			"Id": "Param_Angle_Rotation_5_ArtMesh87",
			"GroupId": "ParamGroup8",
			"Name": "[4]头发1_1"
		},
		{
			"Id": "Param_Angle_Rotation_6_ArtMesh87",
			"GroupId": "ParamGroup8",
			"Name": "[5]头发1_1"
		},
		{
			"Id": "Param_Angle_Rotation_7_ArtMesh87",
			"GroupId": "ParamGroup8",
			"Name": "[6]头发1_1"
		},
		{
			"Id": "Param_Angle_Rotation_1_ArtMesh184",
			"GroupId": "ParamGroup9",
			"Name": "[0]头发1_1透明"
		},
		{
			"Id": "Param_Angle_Rotation_2_ArtMesh184",
			"GroupId": "ParamGroup9",
			"Name": "[1]头发1_1透明"
		},
		{
			"Id": "Param_Angle_Rotation_3_ArtMesh184",
			"GroupId": "ParamGroup9",
			"Name": "[2]头发1_1透明"
		},
		{
			"Id": "Param_Angle_Rotation_4_ArtMesh184",
			"GroupId": "ParamGroup9",
			"Name": "[3]头发1_1透明"
		},
		{
			"Id": "Param_Angle_Rotation_5_ArtMesh184",
			"GroupId": "ParamGroup9",
			"Name": "[4]头发1_1透明"
		},
		{
			"Id": "Param_Angle_Rotation_6_ArtMesh184",
			"GroupId": "ParamGroup9",
			"Name": "[5]头发1_1透明"
		},
		{
			"Id": "Param_Angle_Rotation_7_ArtMesh184",
			"GroupId": "ParamGroup9",
			"Name": "[6]头发1_1透明"
		},
		{
			"Id": "Param_Angle_Rotation_1_ArtMesh149",
			"GroupId": "ParamGroup10",
			"Name": "[0]头发1_1 阴影"
		},
		{
			"Id": "Param_Angle_Rotation_2_ArtMesh149",
			"GroupId": "ParamGroup10",
			"Name": "[1]头发1_1 阴影"
		},
		{
			"Id": "Param_Angle_Rotation_3_ArtMesh149",
			"GroupId": "ParamGroup10",
			"Name": "[2]头发1_1 阴影"
		},
		{
			"Id": "Param_Angle_Rotation_4_ArtMesh149",
			"GroupId": "ParamGroup10",
			"Name": "[3]头发1_1 阴影"
		},
		{
			"Id": "Param_Angle_Rotation_5_ArtMesh149",
			"GroupId": "ParamGroup10",
			"Name": "[4]头发1_1 阴影"
		},
		{
			"Id": "Param_Angle_Rotation_6_ArtMesh149",
			"GroupId": "ParamGroup10",
			"Name": "[5]头发1_1 阴影"
		},
		{
			"Id": "Param_Angle_Rotation_7_ArtMesh149",
			"GroupId": "ParamGroup10",
			"Name": "[6]头发1_1 阴影"
		},
		{
			"Id": "Param_Angle_Rotation_1_ArtMesh88",
			"GroupId": "ParamGroup11",
			"Name": "[0]头发2_1"
		},
		{
			"Id": "Param_Angle_Rotation_2_ArtMesh88",
			"GroupId": "ParamGroup11",
			"Name": "[1]头发2_1"
		},
		{
			"Id": "Param_Angle_Rotation_3_ArtMesh88",
			"GroupId": "ParamGroup11",
			"Name": "[2]头发2_1"
		},
		{
			"Id": "Param_Angle_Rotation_4_ArtMesh88",
			"GroupId": "ParamGroup11",
			"Name": "[3]头发2_1"
		},
		{
			"Id": "Param_Angle_Rotation_5_ArtMesh88",
			"GroupId": "ParamGroup11",
			"Name": "[4]头发2_1"
		},
		{
			"Id": "Param_Angle_Rotation_6_ArtMesh88",
			"GroupId": "ParamGroup11",
			"Name": "[5]头发2_1"
		},
		{
			"Id": "Param_Angle_Rotation_7_ArtMesh88",
			"GroupId": "ParamGroup11",
			"Name": "[6]头发2_1"
		},
		{
			"Id": "Param_Angle_Rotation_1_ArtMesh185",
			"GroupId": "ParamGroup12",
			"Name": "[0]头发2_1透明"
		},
		{
			"Id": "Param_Angle_Rotation_2_ArtMesh185",
			"GroupId": "ParamGroup12",
			"Name": "[1]头发2_1透明"
		},
		{
			"Id": "Param_Angle_Rotation_3_ArtMesh185",
			"GroupId": "ParamGroup12",
			"Name": "[2]头发2_1透明"
		},
		{
			"Id": "Param_Angle_Rotation_4_ArtMesh185",
			"GroupId": "ParamGroup12",
			"Name": "[3]头发2_1透明"
		},
		{
			"Id": "Param_Angle_Rotation_5_ArtMesh185",
			"GroupId": "ParamGroup12",
			"Name": "[4]头发2_1透明"
		},
		{
			"Id": "Param_Angle_Rotation_6_ArtMesh185",
			"GroupId": "ParamGroup12",
			"Name": "[5]头发2_1透明"
		},
		{
			"Id": "Param_Angle_Rotation_7_ArtMesh185",
			"GroupId": "ParamGroup12",
			"Name": "[6]头发2_1透明"
		},
		{
			"Id": "Param_Angle_Rotation_1_ArtMesh150",
			"GroupId": "ParamGroup13",
			"Name": "[0]头发2_1阴影"
		},
		{
			"Id": "Param_Angle_Rotation_2_ArtMesh150",
			"GroupId": "ParamGroup13",
			"Name": "[1]头发2_1阴影"
		},
		{
			"Id": "Param_Angle_Rotation_3_ArtMesh150",
			"GroupId": "ParamGroup13",
			"Name": "[2]头发2_1阴影"
		},
		{
			"Id": "Param_Angle_Rotation_4_ArtMesh150",
			"GroupId": "ParamGroup13",
			"Name": "[3]头发2_1阴影"
		},
		{
			"Id": "Param_Angle_Rotation_5_ArtMesh150",
			"GroupId": "ParamGroup13",
			"Name": "[4]头发2_1阴影"
		},
		{
			"Id": "Param_Angle_Rotation_6_ArtMesh150",
			"GroupId": "ParamGroup13",
			"Name": "[5]头发2_1阴影"
		},
		{
			"Id": "Param_Angle_Rotation_7_ArtMesh150",
			"GroupId": "ParamGroup13",
			"Name": "[6]头发2_1阴影"
		},
		{
			"Id": "Param_Angle_Rotation_1_ArtMesh187",
			"GroupId": "ParamGroup15",
			"Name": "[0]发卡透明"
		},
		{
			"Id": "Param_Angle_Rotation_2_ArtMesh187",
			"GroupId": "ParamGroup15",
			"Name": "[1]发卡透明"
		},
		{
			"Id": "Param_Angle_Rotation_3_ArtMesh187",
			"GroupId": "ParamGroup15",
			"Name": "[2]发卡透明"
		},
		{
			"Id": "Param_Angle_Rotation_4_ArtMesh187",
			"GroupId": "ParamGroup15",
			"Name": "[3]发卡透明"
		},
		{
			"Id": "Param_Angle_Rotation_5_ArtMesh187",
			"GroupId": "ParamGroup15",
			"Name": "[4]发卡透明"
		},
		{
			"Id": "Param_Angle_Rotation_6_ArtMesh187",
			"GroupId": "ParamGroup15",
			"Name": "[5]发卡透明"
		},
		{
			"Id": "Param_Angle_Rotation_7_ArtMesh187",
			"GroupId": "ParamGroup15",
			"Name": "[6]发卡透明"
		},
		{
			"Id": "Param_Angle_Rotation_1_ArtMesh91",
			"GroupId": "ParamGroup16",
			"Name": "[0]发卡"
		},
		{
			"Id": "Param_Angle_Rotation_2_ArtMesh91",
			"GroupId": "ParamGroup16",
			"Name": "[1]发卡"
		},
		{
			"Id": "Param_Angle_Rotation_3_ArtMesh91",
			"GroupId": "ParamGroup16",
			"Name": "[2]发卡"
		},
		{
			"Id": "Param_Angle_Rotation_4_ArtMesh91",
			"GroupId": "ParamGroup16",
			"Name": "[3]发卡"
		},
		{
			"Id": "Param_Angle_Rotation_5_ArtMesh91",
			"GroupId": "ParamGroup16",
			"Name": "[4]发卡"
		},
		{
			"Id": "Param_Angle_Rotation_6_ArtMesh91",
			"GroupId": "ParamGroup16",
			"Name": "[5]发卡"
		},
		{
			"Id": "Param_Angle_Rotation_7_ArtMesh91",
			"GroupId": "ParamGroup16",
			"Name": "[6]发卡"
		},
		{
			"Id": "Param_Angle_Rotation_1_ArtMesh190",
			"GroupId": "ParamGroup17",
			"Name": "[0]头发3_2透明"
		},
		{
			"Id": "Param_Angle_Rotation_2_ArtMesh190",
			"GroupId": "ParamGroup17",
			"Name": "[1]头发3_2透明"
		},
		{
			"Id": "Param_Angle_Rotation_3_ArtMesh190",
			"GroupId": "ParamGroup17",
			"Name": "[2]头发3_2透明"
		},
		{
			"Id": "Param_Angle_Rotation_4_ArtMesh190",
			"GroupId": "ParamGroup17",
			"Name": "[3]头发3_2透明"
		},
		{
			"Id": "Param_Angle_Rotation_5_ArtMesh190",
			"GroupId": "ParamGroup17",
			"Name": "[4]头发3_2透明"
		},
		{
			"Id": "Param_Angle_Rotation_6_ArtMesh190",
			"GroupId": "ParamGroup17",
			"Name": "[5]头发3_2透明"
		},
		{
			"Id": "Param_Angle_Rotation_7_ArtMesh190",
			"GroupId": "ParamGroup17",
			"Name": "[6]头发3_2透明"
		},
		{
			"Id": "Param_Angle_Rotation_1_ArtMesh95",
			"GroupId": "ParamGroup18",
			"Name": "[0]头发3_2"
		},
		{
			"Id": "Param_Angle_Rotation_2_ArtMesh95",
			"GroupId": "ParamGroup18",
			"Name": "[1]头发3_2"
		},
		{
			"Id": "Param_Angle_Rotation_3_ArtMesh95",
			"GroupId": "ParamGroup18",
			"Name": "[2]头发3_2"
		},
		{
			"Id": "Param_Angle_Rotation_4_ArtMesh95",
			"GroupId": "ParamGroup18",
			"Name": "[3]头发3_2"
		},
		{
			"Id": "Param_Angle_Rotation_5_ArtMesh95",
			"GroupId": "ParamGroup18",
			"Name": "[4]头发3_2"
		},
		{
			"Id": "Param_Angle_Rotation_6_ArtMesh95",
			"GroupId": "ParamGroup18",
			"Name": "[5]头发3_2"
		},
		{
			"Id": "Param_Angle_Rotation_7_ArtMesh95",
			"GroupId": "ParamGroup18",
			"Name": "[6]头发3_2"
		},
		{
			"Id": "Param_Angle_Rotation_1_ArtMesh207",
			"GroupId": "ParamGroup19",
			"Name": "[0]头发3_2阴影透明"
		},
		{
			"Id": "Param_Angle_Rotation_2_ArtMesh207",
			"GroupId": "ParamGroup19",
			"Name": "[1]头发3_2阴影透明"
		},
		{
			"Id": "Param_Angle_Rotation_3_ArtMesh207",
			"GroupId": "ParamGroup19",
			"Name": "[2]头发3_2阴影透明"
		},
		{
			"Id": "Param_Angle_Rotation_4_ArtMesh207",
			"GroupId": "ParamGroup19",
			"Name": "[3]头发3_2阴影透明"
		},
		{
			"Id": "Param_Angle_Rotation_5_ArtMesh207",
			"GroupId": "ParamGroup19",
			"Name": "[4]头发3_2阴影透明"
		},
		{
			"Id": "Param_Angle_Rotation_6_ArtMesh207",
			"GroupId": "ParamGroup19",
			"Name": "[5]头发3_2阴影透明"
		},
		{
			"Id": "Param_Angle_Rotation_7_ArtMesh207",
			"GroupId": "ParamGroup19",
			"Name": "[6]头发3_2阴影透明"
		},
		{
			"Id": "Param_Angle_Rotation_1_ArtMesh116",
			"GroupId": "ParamGroup20",
			"Name": "[0]头发3_2阴影"
		},
		{
			"Id": "Param_Angle_Rotation_2_ArtMesh116",
			"GroupId": "ParamGroup20",
			"Name": "[1]头发3_2阴影"
		},
		{
			"Id": "Param_Angle_Rotation_3_ArtMesh116",
			"GroupId": "ParamGroup20",
			"Name": "[2]头发3_2阴影"
		},
		{
			"Id": "Param_Angle_Rotation_4_ArtMesh116",
			"GroupId": "ParamGroup20",
			"Name": "[3]头发3_2阴影"
		},
		{
			"Id": "Param_Angle_Rotation_5_ArtMesh116",
			"GroupId": "ParamGroup20",
			"Name": "[4]头发3_2阴影"
		},
		{
			"Id": "Param_Angle_Rotation_6_ArtMesh116",
			"GroupId": "ParamGroup20",
			"Name": "[5]头发3_2阴影"
		},
		{
			"Id": "Param_Angle_Rotation_7_ArtMesh116",
			"GroupId": "ParamGroup20",
			"Name": "[6]头发3_2阴影"
		},
		{
			"Id": "Param_Angle_Rotation_1_ArtMesh186",
			"GroupId": "ParamGroup21",
			"Name": "[0]头发3_1透明"
		},
		{
			"Id": "Param_Angle_Rotation_2_ArtMesh186",
			"GroupId": "ParamGroup21",
			"Name": "[1]头发3_1透明"
		},
		{
			"Id": "Param_Angle_Rotation_3_ArtMesh186",
			"GroupId": "ParamGroup21",
			"Name": "[2]头发3_1透明"
		},
		{
			"Id": "Param_Angle_Rotation_4_ArtMesh186",
			"GroupId": "ParamGroup21",
			"Name": "[3]头发3_1透明"
		},
		{
			"Id": "Param_Angle_Rotation_5_ArtMesh186",
			"GroupId": "ParamGroup21",
			"Name": "[4]头发3_1透明"
		},
		{
			"Id": "Param_Angle_Rotation_6_ArtMesh186",
			"GroupId": "ParamGroup21",
			"Name": "[5]头发3_1透明"
		},
		{
			"Id": "Param_Angle_Rotation_7_ArtMesh186",
			"GroupId": "ParamGroup21",
			"Name": "[6]头发3_1透明"
		},
		{
			"Id": "Param_Angle_Rotation_1_ArtMesh92",
			"GroupId": "ParamGroup22",
			"Name": "[0]头发3_1"
		},
		{
			"Id": "Param_Angle_Rotation_2_ArtMesh92",
			"GroupId": "ParamGroup22",
			"Name": "[1]头发3_1"
		},
		{
			"Id": "Param_Angle_Rotation_3_ArtMesh92",
			"GroupId": "ParamGroup22",
			"Name": "[2]头发3_1"
		},
		{
			"Id": "Param_Angle_Rotation_4_ArtMesh92",
			"GroupId": "ParamGroup22",
			"Name": "[3]头发3_1"
		},
		{
			"Id": "Param_Angle_Rotation_5_ArtMesh92",
			"GroupId": "ParamGroup22",
			"Name": "[4]头发3_1"
		},
		{
			"Id": "Param_Angle_Rotation_6_ArtMesh92",
			"GroupId": "ParamGroup22",
			"Name": "[5]头发3_1"
		},
		{
			"Id": "Param_Angle_Rotation_7_ArtMesh92",
			"GroupId": "ParamGroup22",
			"Name": "[6]头发3_1"
		},
		{
			"Id": "Param_Angle_Rotation_1_ArtMesh198",
			"GroupId": "ParamGroup23",
			"Name": "[0]头发3_1阴影透明"
		},
		{
			"Id": "Param_Angle_Rotation_2_ArtMesh198",
			"GroupId": "ParamGroup23",
			"Name": "[1]头发3_1阴影透明"
		},
		{
			"Id": "Param_Angle_Rotation_3_ArtMesh198",
			"GroupId": "ParamGroup23",
			"Name": "[2]头发3_1阴影透明"
		},
		{
			"Id": "Param_Angle_Rotation_4_ArtMesh198",
			"GroupId": "ParamGroup23",
			"Name": "[3]头发3_1阴影透明"
		},
		{
			"Id": "Param_Angle_Rotation_5_ArtMesh198",
			"GroupId": "ParamGroup23",
			"Name": "[4]头发3_1阴影透明"
		},
		{
			"Id": "Param_Angle_Rotation_6_ArtMesh198",
			"GroupId": "ParamGroup23",
			"Name": "[5]头发3_1阴影透明"
		},
		{
			"Id": "Param_Angle_Rotation_7_ArtMesh198",
			"GroupId": "ParamGroup23",
			"Name": "[6]头发3_1阴影透明"
		},
		{
			"Id": "Param_Angle_Rotation_1_ArtMesh107",
			"GroupId": "ParamGroup24",
			"Name": "[0]头发3_1阴影"
		},
		{
			"Id": "Param_Angle_Rotation_2_ArtMesh107",
			"GroupId": "ParamGroup24",
			"Name": "[1]头发3_1阴影"
		},
		{
			"Id": "Param_Angle_Rotation_3_ArtMesh107",
			"GroupId": "ParamGroup24",
			"Name": "[2]头发3_1阴影"
		},
		{
			"Id": "Param_Angle_Rotation_4_ArtMesh107",
			"GroupId": "ParamGroup24",
			"Name": "[3]头发3_1阴影"
		},
		{
			"Id": "Param_Angle_Rotation_5_ArtMesh107",
			"GroupId": "ParamGroup24",
			"Name": "[4]头发3_1阴影"
		},
		{
			"Id": "Param_Angle_Rotation_6_ArtMesh107",
			"GroupId": "ParamGroup24",
			"Name": "[5]头发3_1阴影"
		},
		{
			"Id": "Param_Angle_Rotation_7_ArtMesh107",
			"GroupId": "ParamGroup24",
			"Name": "[6]头发3_1阴影"
		},
		{
			"Id": "Param_Angle_Rotation_1_ArtMesh93",
			"GroupId": "ParamGroup25",
			"Name": "[0]头发2_2"
		},
		{
			"Id": "Param_Angle_Rotation_2_ArtMesh93",
			"GroupId": "ParamGroup25",
			"Name": "[1]头发2_2"
		},
		{
			"Id": "Param_Angle_Rotation_3_ArtMesh93",
			"GroupId": "ParamGroup25",
			"Name": "[2]头发2_2"
		},
		{
			"Id": "Param_Angle_Rotation_4_ArtMesh93",
			"GroupId": "ParamGroup25",
			"Name": "[3]头发2_2"
		},
		{
			"Id": "Param_Angle_Rotation_5_ArtMesh93",
			"GroupId": "ParamGroup25",
			"Name": "[4]头发2_2"
		},
		{
			"Id": "Param_Angle_Rotation_6_ArtMesh93",
			"GroupId": "ParamGroup25",
			"Name": "[5]头发2_2"
		},
		{
			"Id": "Param_Angle_Rotation_7_ArtMesh93",
			"GroupId": "ParamGroup25",
			"Name": "[6]头发2_2"
		},
		{
			"Id": "Param_Angle_Rotation_1_ArtMesh94",
			"GroupId": "ParamGroup26",
			"Name": "[0]头发1_2"
		},
		{
			"Id": "Param_Angle_Rotation_2_ArtMesh94",
			"GroupId": "ParamGroup26",
			"Name": "[1]头发1_2"
		},
		{
			"Id": "Param_Angle_Rotation_3_ArtMesh94",
			"GroupId": "ParamGroup26",
			"Name": "[2]头发1_2"
		},
		{
			"Id": "Param_Angle_Rotation_4_ArtMesh94",
			"GroupId": "ParamGroup26",
			"Name": "[3]头发1_2"
		},
		{
			"Id": "Param_Angle_Rotation_5_ArtMesh94",
			"GroupId": "ParamGroup26",
			"Name": "[4]头发1_2"
		},
		{
			"Id": "Param_Angle_Rotation_1_ArtMesh188",
			"GroupId": "ParamGroup27",
			"Name": "[0]头发5_2透明"
		},
		{
			"Id": "Param_Angle_Rotation_2_ArtMesh188",
			"GroupId": "ParamGroup27",
			"Name": "[1]头发5_2透明"
		},
		{
			"Id": "Param_Angle_Rotation_3_ArtMesh188",
			"GroupId": "ParamGroup27",
			"Name": "[2]头发5_2透明"
		},
		{
			"Id": "Param_Angle_Rotation_4_ArtMesh188",
			"GroupId": "ParamGroup27",
			"Name": "[3]头发5_2透明"
		},
		{
			"Id": "Param_Angle_Rotation_5_ArtMesh188",
			"GroupId": "ParamGroup27",
			"Name": "[4]头发5_2透明"
		},
		{
			"Id": "Param_Angle_Rotation_6_ArtMesh188",
			"GroupId": "ParamGroup27",
			"Name": "[5]头发5_2透明"
		},
		{
			"Id": "Param_Angle_Rotation_7_ArtMesh188",
			"GroupId": "ParamGroup27",
			"Name": "[6]头发5_2透明"
		},
		{
			"Id": "Param_Angle_Rotation_1_ArtMesh96",
			"GroupId": "ParamGroup28",
			"Name": "[0]头发5_2"
		},
		{
			"Id": "Param_Angle_Rotation_2_ArtMesh96",
			"GroupId": "ParamGroup28",
			"Name": "[1]头发5_2"
		},
		{
			"Id": "Param_Angle_Rotation_3_ArtMesh96",
			"GroupId": "ParamGroup28",
			"Name": "[2]头发5_2"
		},
		{
			"Id": "Param_Angle_Rotation_4_ArtMesh96",
			"GroupId": "ParamGroup28",
			"Name": "[3]头发5_2"
		},
		{
			"Id": "Param_Angle_Rotation_5_ArtMesh96",
			"GroupId": "ParamGroup28",
			"Name": "[4]头发5_2"
		},
		{
			"Id": "Param_Angle_Rotation_6_ArtMesh96",
			"GroupId": "ParamGroup28",
			"Name": "[5]头发5_2"
		},
		{
			"Id": "Param_Angle_Rotation_7_ArtMesh96",
			"GroupId": "ParamGroup28",
			"Name": "[6]头发5_2"
		},
		{
			"Id": "Param_Angle_Rotation_1_ArtMesh205",
			"GroupId": "ParamGroup29",
			"Name": "[0]头发5_2阴影透明"
		},
		{
			"Id": "Param_Angle_Rotation_2_ArtMesh205",
			"GroupId": "ParamGroup29",
			"Name": "[1]头发5_2阴影透明"
		},
		{
			"Id": "Param_Angle_Rotation_3_ArtMesh205",
			"GroupId": "ParamGroup29",
			"Name": "[2]头发5_2阴影透明"
		},
		{
			"Id": "Param_Angle_Rotation_4_ArtMesh205",
			"GroupId": "ParamGroup29",
			"Name": "[3]头发5_2阴影透明"
		},
		{
			"Id": "Param_Angle_Rotation_5_ArtMesh205",
			"GroupId": "ParamGroup29",
			"Name": "[4]头发5_2阴影透明"
		},
		{
			"Id": "Param_Angle_Rotation_6_ArtMesh205",
			"GroupId": "ParamGroup29",
			"Name": "[5]头发5_2阴影透明"
		},
		{
			"Id": "Param_Angle_Rotation_7_ArtMesh205",
			"GroupId": "ParamGroup29",
			"Name": "[6]头发5_2阴影透明"
		},
		{
			"Id": "Param_Angle_Rotation_1_ArtMesh114",
			"GroupId": "ParamGroup30",
			"Name": "[0]头发5_2阴影"
		},
		{
			"Id": "Param_Angle_Rotation_2_ArtMesh114",
			"GroupId": "ParamGroup30",
			"Name": "[1]头发5_2阴影"
		},
		{
			"Id": "Param_Angle_Rotation_3_ArtMesh114",
			"GroupId": "ParamGroup30",
			"Name": "[2]头发5_2阴影"
		},
		{
			"Id": "Param_Angle_Rotation_4_ArtMesh114",
			"GroupId": "ParamGroup30",
			"Name": "[3]头发5_2阴影"
		},
		{
			"Id": "Param_Angle_Rotation_5_ArtMesh114",
			"GroupId": "ParamGroup30",
			"Name": "[4]头发5_2阴影"
		},
		{
			"Id": "Param_Angle_Rotation_6_ArtMesh114",
			"GroupId": "ParamGroup30",
			"Name": "[5]头发5_2阴影"
		},
		{
			"Id": "Param_Angle_Rotation_7_ArtMesh114",
			"GroupId": "ParamGroup30",
			"Name": "[6]头发5_2阴影"
		},
		{
			"Id": "Param_Angle_Rotation_1_ArtMesh189",
			"GroupId": "ParamGroup31",
			"Name": "[0]头发4_2透明"
		},
		{
			"Id": "Param_Angle_Rotation_2_ArtMesh189",
			"GroupId": "ParamGroup31",
			"Name": "[1]头发4_2透明"
		},
		{
			"Id": "Param_Angle_Rotation_3_ArtMesh189",
			"GroupId": "ParamGroup31",
			"Name": "[2]头发4_2透明"
		},
		{
			"Id": "Param_Angle_Rotation_4_ArtMesh189",
			"GroupId": "ParamGroup31",
			"Name": "[3]头发4_2透明"
		},
		{
			"Id": "Param_Angle_Rotation_5_ArtMesh189",
			"GroupId": "ParamGroup31",
			"Name": "[4]头发4_2透明"
		},
		{
			"Id": "Param_Angle_Rotation_6_ArtMesh189",
			"GroupId": "ParamGroup31",
			"Name": "[5]头发4_2透明"
		},
		{
			"Id": "Param_Angle_Rotation_7_ArtMesh189",
			"GroupId": "ParamGroup31",
			"Name": "[6]头发4_2透明"
		},
		{
			"Id": "Param_Angle_Rotation_1_ArtMesh97",
			"GroupId": "ParamGroup32",
			"Name": "[0]头发4_2"
		},
		{
			"Id": "Param_Angle_Rotation_2_ArtMesh97",
			"GroupId": "ParamGroup32",
			"Name": "[1]头发4_2"
		},
		{
			"Id": "Param_Angle_Rotation_3_ArtMesh97",
			"GroupId": "ParamGroup32",
			"Name": "[2]头发4_2"
		},
		{
			"Id": "Param_Angle_Rotation_4_ArtMesh97",
			"GroupId": "ParamGroup32",
			"Name": "[3]头发4_2"
		},
		{
			"Id": "Param_Angle_Rotation_5_ArtMesh97",
			"GroupId": "ParamGroup32",
			"Name": "[4]头发4_2"
		},
		{
			"Id": "Param_Angle_Rotation_6_ArtMesh97",
			"GroupId": "ParamGroup32",
			"Name": "[5]头发4_2"
		},
		{
			"Id": "Param_Angle_Rotation_7_ArtMesh97",
			"GroupId": "ParamGroup32",
			"Name": "[6]头发4_2"
		},
		{
			"Id": "Param_Angle_Rotation_1_ArtMesh206",
			"GroupId": "ParamGroup33",
			"Name": "[0]头发4_2阴影透明"
		},
		{
			"Id": "Param_Angle_Rotation_2_ArtMesh206",
			"GroupId": "ParamGroup33",
			"Name": "[1]头发4_2阴影透明"
		},
		{
			"Id": "Param_Angle_Rotation_3_ArtMesh206",
			"GroupId": "ParamGroup33",
			"Name": "[2]头发4_2阴影透明"
		},
		{
			"Id": "Param_Angle_Rotation_4_ArtMesh206",
			"GroupId": "ParamGroup33",
			"Name": "[3]头发4_2阴影透明"
		},
		{
			"Id": "Param_Angle_Rotation_5_ArtMesh206",
			"GroupId": "ParamGroup33",
			"Name": "[4]头发4_2阴影透明"
		},
		{
			"Id": "Param_Angle_Rotation_6_ArtMesh206",
			"GroupId": "ParamGroup33",
			"Name": "[5]头发4_2阴影透明"
		},
		{
			"Id": "Param_Angle_Rotation_7_ArtMesh206",
			"GroupId": "ParamGroup33",
			"Name": "[6]头发4_2阴影透明"
		},
		{
			"Id": "Param_Angle_Rotation_1_ArtMesh115",
			"GroupId": "ParamGroup34",
			"Name": "[0]头发4_2阴影"
		},
		{
			"Id": "Param_Angle_Rotation_2_ArtMesh115",
			"GroupId": "ParamGroup34",
			"Name": "[1]头发4_2阴影"
		},
		{
			"Id": "Param_Angle_Rotation_3_ArtMesh115",
			"GroupId": "ParamGroup34",
			"Name": "[2]头发4_2阴影"
		},
		{
			"Id": "Param_Angle_Rotation_4_ArtMesh115",
			"GroupId": "ParamGroup34",
			"Name": "[3]头发4_2阴影"
		},
		{
			"Id": "Param_Angle_Rotation_5_ArtMesh115",
			"GroupId": "ParamGroup34",
			"Name": "[4]头发4_2阴影"
		},
		{
			"Id": "Param_Angle_Rotation_6_ArtMesh115",
			"GroupId": "ParamGroup34",
			"Name": "[5]头发4_2阴影"
		},
		{
			"Id": "Param_Angle_Rotation_7_ArtMesh115",
			"GroupId": "ParamGroup34",
			"Name": "[6]头发4_2阴影"
		},
		{
			"Id": "Param_Angle_Rotation_1_ArtMesh191",
			"GroupId": "ParamGroup35",
			"Name": "[0]头发6_2透明"
		},
		{
			"Id": "Param_Angle_Rotation_2_ArtMesh191",
			"GroupId": "ParamGroup35",
			"Name": "[1]头发6_2透明"
		},
		{
			"Id": "Param_Angle_Rotation_3_ArtMesh191",
			"GroupId": "ParamGroup35",
			"Name": "[2]头发6_2透明"
		},
		{
			"Id": "Param_Angle_Rotation_4_ArtMesh191",
			"GroupId": "ParamGroup35",
			"Name": "[3]头发6_2透明"
		},
		{
			"Id": "Param_Angle_Rotation_5_ArtMesh191",
			"GroupId": "ParamGroup35",
			"Name": "[4]头发6_2透明"
		},
		{
			"Id": "Param_Angle_Rotation_6_ArtMesh191",
			"GroupId": "ParamGroup35",
			"Name": "[5]头发6_2透明"
		},
		{
			"Id": "Param_Angle_Rotation_7_ArtMesh191",
			"GroupId": "ParamGroup35",
			"Name": "[6]头发6_2透明"
		},
		{
			"Id": "Param_Angle_Rotation_1_ArtMesh98",
			"GroupId": "ParamGroup36",
			"Name": "[0]头发6_2"
		},
		{
			"Id": "Param_Angle_Rotation_2_ArtMesh98",
			"GroupId": "ParamGroup36",
			"Name": "[1]头发6_2"
		},
		{
			"Id": "Param_Angle_Rotation_3_ArtMesh98",
			"GroupId": "ParamGroup36",
			"Name": "[2]头发6_2"
		},
		{
			"Id": "Param_Angle_Rotation_4_ArtMesh98",
			"GroupId": "ParamGroup36",
			"Name": "[3]头发6_2"
		},
		{
			"Id": "Param_Angle_Rotation_5_ArtMesh98",
			"GroupId": "ParamGroup36",
			"Name": "[4]头发6_2"
		},
		{
			"Id": "Param_Angle_Rotation_6_ArtMesh98",
			"GroupId": "ParamGroup36",
			"Name": "[5]头发6_2"
		},
		{
			"Id": "Param_Angle_Rotation_7_ArtMesh98",
			"GroupId": "ParamGroup36",
			"Name": "[6]头发6_2"
		},
		{
			"Id": "Param_Angle_Rotation_1_ArtMesh204",
			"GroupId": "ParamGroup37",
			"Name": "[0]头发6_2阴影透明"
		},
		{
			"Id": "Param_Angle_Rotation_2_ArtMesh204",
			"GroupId": "ParamGroup37",
			"Name": "[1]头发6_2阴影透明"
		},
		{
			"Id": "Param_Angle_Rotation_3_ArtMesh204",
			"GroupId": "ParamGroup37",
			"Name": "[2]头发6_2阴影透明"
		},
		{
			"Id": "Param_Angle_Rotation_4_ArtMesh204",
			"GroupId": "ParamGroup37",
			"Name": "[3]头发6_2阴影透明"
		},
		{
			"Id": "Param_Angle_Rotation_5_ArtMesh204",
			"GroupId": "ParamGroup37",
			"Name": "[4]头发6_2阴影透明"
		},
		{
			"Id": "Param_Angle_Rotation_6_ArtMesh204",
			"GroupId": "ParamGroup37",
			"Name": "[5]头发6_2阴影透明"
		},
		{
			"Id": "Param_Angle_Rotation_7_ArtMesh204",
			"GroupId": "ParamGroup37",
			"Name": "[6]头发6_2阴影透明"
		},
		{
			"Id": "Param_Angle_Rotation_1_ArtMesh113",
			"GroupId": "ParamGroup38",
			"Name": "[0]头发6_2阴影"
		},
		{
			"Id": "Param_Angle_Rotation_2_ArtMesh113",
			"GroupId": "ParamGroup38",
			"Name": "[1]头发6_2阴影"
		},
		{
			"Id": "Param_Angle_Rotation_3_ArtMesh113",
			"GroupId": "ParamGroup38",
			"Name": "[2]头发6_2阴影"
		},
		{
			"Id": "Param_Angle_Rotation_4_ArtMesh113",
			"GroupId": "ParamGroup38",
			"Name": "[3]头发6_2阴影"
		},
		{
			"Id": "Param_Angle_Rotation_5_ArtMesh113",
			"GroupId": "ParamGroup38",
			"Name": "[4]头发6_2阴影"
		},
		{
			"Id": "Param_Angle_Rotation_6_ArtMesh113",
			"GroupId": "ParamGroup38",
			"Name": "[5]头发6_2阴影"
		},
		{
			"Id": "Param_Angle_Rotation_7_ArtMesh113",
			"GroupId": "ParamGroup38",
			"Name": "[6]头发6_2阴影"
		},
		{
			"Id": "Param_Angle_Rotation_1_ArtMesh192",
			"GroupId": "ParamGroup39",
			"Name": "[0]头发7_2透明"
		},
		{
			"Id": "Param_Angle_Rotation_2_ArtMesh192",
			"GroupId": "ParamGroup39",
			"Name": "[1]头发7_2透明"
		},
		{
			"Id": "Param_Angle_Rotation_3_ArtMesh192",
			"GroupId": "ParamGroup39",
			"Name": "[2]头发7_2透明"
		},
		{
			"Id": "Param_Angle_Rotation_4_ArtMesh192",
			"GroupId": "ParamGroup39",
			"Name": "[3]头发7_2透明"
		},
		{
			"Id": "Param_Angle_Rotation_5_ArtMesh192",
			"GroupId": "ParamGroup39",
			"Name": "[4]头发7_2透明"
		},
		{
			"Id": "Param_Angle_Rotation_6_ArtMesh192",
			"GroupId": "ParamGroup39",
			"Name": "[5]头发7_2透明"
		},
		{
			"Id": "Param_Angle_Rotation_7_ArtMesh192",
			"GroupId": "ParamGroup39",
			"Name": "[6]头发7_2透明"
		},
		{
			"Id": "Param_Angle_Rotation_1_ArtMesh99",
			"GroupId": "ParamGroup40",
			"Name": "[0]头发7_2"
		},
		{
			"Id": "Param_Angle_Rotation_2_ArtMesh99",
			"GroupId": "ParamGroup40",
			"Name": "[1]头发7_2"
		},
		{
			"Id": "Param_Angle_Rotation_3_ArtMesh99",
			"GroupId": "ParamGroup40",
			"Name": "[2]头发7_2"
		},
		{
			"Id": "Param_Angle_Rotation_4_ArtMesh99",
			"GroupId": "ParamGroup40",
			"Name": "[3]头发7_2"
		},
		{
			"Id": "Param_Angle_Rotation_5_ArtMesh99",
			"GroupId": "ParamGroup40",
			"Name": "[4]头发7_2"
		},
		{
			"Id": "Param_Angle_Rotation_6_ArtMesh99",
			"GroupId": "ParamGroup40",
			"Name": "[5]头发7_2"
		},
		{
			"Id": "Param_Angle_Rotation_7_ArtMesh99",
			"GroupId": "ParamGroup40",
			"Name": "[6]头发7_2"
		},
		{
			"Id": "Param_Angle_Rotation_1_ArtMesh203",
			"GroupId": "ParamGroup41",
			"Name": "[0]头发7_2阴影透明"
		},
		{
			"Id": "Param_Angle_Rotation_2_ArtMesh203",
			"GroupId": "ParamGroup41",
			"Name": "[1]头发7_2阴影透明"
		},
		{
			"Id": "Param_Angle_Rotation_3_ArtMesh203",
			"GroupId": "ParamGroup41",
			"Name": "[2]头发7_2阴影透明"
		},
		{
			"Id": "Param_Angle_Rotation_4_ArtMesh203",
			"GroupId": "ParamGroup41",
			"Name": "[3]头发7_2阴影透明"
		},
		{
			"Id": "Param_Angle_Rotation_5_ArtMesh203",
			"GroupId": "ParamGroup41",
			"Name": "[4]头发7_2阴影透明"
		},
		{
			"Id": "Param_Angle_Rotation_6_ArtMesh203",
			"GroupId": "ParamGroup41",
			"Name": "[5]头发7_2阴影透明"
		},
		{
			"Id": "Param_Angle_Rotation_7_ArtMesh203",
			"GroupId": "ParamGroup41",
			"Name": "[6]头发7_2阴影透明"
		},
		{
			"Id": "Param_Angle_Rotation_1_ArtMesh112",
			"GroupId": "ParamGroup42",
			"Name": "[0]头发7_2阴影"
		},
		{
			"Id": "Param_Angle_Rotation_2_ArtMesh112",
			"GroupId": "ParamGroup42",
			"Name": "[1]头发7_2阴影"
		},
		{
			"Id": "Param_Angle_Rotation_3_ArtMesh112",
			"GroupId": "ParamGroup42",
			"Name": "[2]头发7_2阴影"
		},
		{
			"Id": "Param_Angle_Rotation_4_ArtMesh112",
			"GroupId": "ParamGroup42",
			"Name": "[3]头发7_2阴影"
		},
		{
			"Id": "Param_Angle_Rotation_5_ArtMesh112",
			"GroupId": "ParamGroup42",
			"Name": "[4]头发7_2阴影"
		},
		{
			"Id": "Param_Angle_Rotation_6_ArtMesh112",
			"GroupId": "ParamGroup42",
			"Name": "[5]头发7_2阴影"
		},
		{
			"Id": "Param_Angle_Rotation_7_ArtMesh112",
			"GroupId": "ParamGroup42",
			"Name": "[6]头发7_2阴影"
		},
		{
			"Id": "Param_Angle_Rotation_1_ArtMesh193",
			"GroupId": "ParamGroup43",
			"Name": "[0]头发9_2透明"
		},
		{
			"Id": "Param_Angle_Rotation_2_ArtMesh193",
			"GroupId": "ParamGroup43",
			"Name": "[1]头发9_2透明"
		},
		{
			"Id": "Param_Angle_Rotation_3_ArtMesh193",
			"GroupId": "ParamGroup43",
			"Name": "[2]头发9_2透明"
		},
		{
			"Id": "Param_Angle_Rotation_4_ArtMesh193",
			"GroupId": "ParamGroup43",
			"Name": "[3]头发9_2透明"
		},
		{
			"Id": "Param_Angle_Rotation_5_ArtMesh193",
			"GroupId": "ParamGroup43",
			"Name": "[4]头发9_2透明"
		},
		{
			"Id": "Param_Angle_Rotation_6_ArtMesh193",
			"GroupId": "ParamGroup43",
			"Name": "[5]头发9_2透明"
		},
		{
			"Id": "Param_Angle_Rotation_7_ArtMesh193",
			"GroupId": "ParamGroup43",
			"Name": "[6]头发9_2透明"
		},
		{
			"Id": "Param_Angle_Rotation_1_ArtMesh100",
			"GroupId": "ParamGroup44",
			"Name": "[0]头发9_2"
		},
		{
			"Id": "Param_Angle_Rotation_2_ArtMesh100",
			"GroupId": "ParamGroup44",
			"Name": "[1]头发9_2"
		},
		{
			"Id": "Param_Angle_Rotation_3_ArtMesh100",
			"GroupId": "ParamGroup44",
			"Name": "[2]头发9_2"
		},
		{
			"Id": "Param_Angle_Rotation_4_ArtMesh100",
			"GroupId": "ParamGroup44",
			"Name": "[3]头发9_2"
		},
		{
			"Id": "Param_Angle_Rotation_5_ArtMesh100",
			"GroupId": "ParamGroup44",
			"Name": "[4]头发9_2"
		},
		{
			"Id": "Param_Angle_Rotation_6_ArtMesh100",
			"GroupId": "ParamGroup44",
			"Name": "[5]头发9_2"
		},
		{
			"Id": "Param_Angle_Rotation_7_ArtMesh100",
			"GroupId": "ParamGroup44",
			"Name": "[6]头发9_2"
		},
		{
			"Id": "Param_Angle_Rotation_1_ArtMesh201",
			"GroupId": "ParamGroup45",
			"Name": "[0]头发9_2阴影透明"
		},
		{
			"Id": "Param_Angle_Rotation_2_ArtMesh201",
			"GroupId": "ParamGroup45",
			"Name": "[1]头发9_2阴影透明"
		},
		{
			"Id": "Param_Angle_Rotation_3_ArtMesh201",
			"GroupId": "ParamGroup45",
			"Name": "[2]头发9_2阴影透明"
		},
		{
			"Id": "Param_Angle_Rotation_4_ArtMesh201",
			"GroupId": "ParamGroup45",
			"Name": "[3]头发9_2阴影透明"
		},
		{
			"Id": "Param_Angle_Rotation_5_ArtMesh201",
			"GroupId": "ParamGroup45",
			"Name": "[4]头发9_2阴影透明"
		},
		{
			"Id": "Param_Angle_Rotation_6_ArtMesh201",
			"GroupId": "ParamGroup45",
			"Name": "[5]头发9_2阴影透明"
		},
		{
			"Id": "Param_Angle_Rotation_7_ArtMesh201",
			"GroupId": "ParamGroup45",
			"Name": "[6]头发9_2阴影透明"
		},
		{
			"Id": "Param_Angle_Rotation_1_ArtMesh110",
			"GroupId": "ParamGroup46",
			"Name": "[0]头发9_2阴影"
		},
		{
			"Id": "Param_Angle_Rotation_2_ArtMesh110",
			"GroupId": "ParamGroup46",
			"Name": "[1]头发9_2阴影"
		},
		{
			"Id": "Param_Angle_Rotation_3_ArtMesh110",
			"GroupId": "ParamGroup46",
			"Name": "[2]头发9_2阴影"
		},
		{
			"Id": "Param_Angle_Rotation_4_ArtMesh110",
			"GroupId": "ParamGroup46",
			"Name": "[3]头发9_2阴影"
		},
		{
			"Id": "Param_Angle_Rotation_5_ArtMesh110",
			"GroupId": "ParamGroup46",
			"Name": "[4]头发9_2阴影"
		},
		{
			"Id": "Param_Angle_Rotation_6_ArtMesh110",
			"GroupId": "ParamGroup46",
			"Name": "[5]头发9_2阴影"
		},
		{
			"Id": "Param_Angle_Rotation_7_ArtMesh110",
			"GroupId": "ParamGroup46",
			"Name": "[6]头发9_2阴影"
		},
		{
			"Id": "Param_Angle_Rotation_1_ArtMesh194",
			"GroupId": "ParamGroup47",
			"Name": "[0]头发8_2透明"
		},
		{
			"Id": "Param_Angle_Rotation_2_ArtMesh194",
			"GroupId": "ParamGroup47",
			"Name": "[1]头发8_2透明"
		},
		{
			"Id": "Param_Angle_Rotation_3_ArtMesh194",
			"GroupId": "ParamGroup47",
			"Name": "[2]头发8_2透明"
		},
		{
			"Id": "Param_Angle_Rotation_4_ArtMesh194",
			"GroupId": "ParamGroup47",
			"Name": "[3]头发8_2透明"
		},
		{
			"Id": "Param_Angle_Rotation_5_ArtMesh194",
			"GroupId": "ParamGroup47",
			"Name": "[4]头发8_2透明"
		},
		{
			"Id": "Param_Angle_Rotation_6_ArtMesh194",
			"GroupId": "ParamGroup47",
			"Name": "[5]头发8_2透明"
		},
		{
			"Id": "Param_Angle_Rotation_7_ArtMesh194",
			"GroupId": "ParamGroup47",
			"Name": "[6]头发8_2透明"
		},
		{
			"Id": "Param_Angle_Rotation_1_ArtMesh101",
			"GroupId": "ParamGroup48",
			"Name": "[0]头发8_2"
		},
		{
			"Id": "Param_Angle_Rotation_2_ArtMesh101",
			"GroupId": "ParamGroup48",
			"Name": "[1]头发8_2"
		},
		{
			"Id": "Param_Angle_Rotation_3_ArtMesh101",
			"GroupId": "ParamGroup48",
			"Name": "[2]头发8_2"
		},
		{
			"Id": "Param_Angle_Rotation_4_ArtMesh101",
			"GroupId": "ParamGroup48",
			"Name": "[3]头发8_2"
		},
		{
			"Id": "Param_Angle_Rotation_5_ArtMesh101",
			"GroupId": "ParamGroup48",
			"Name": "[4]头发8_2"
		},
		{
			"Id": "Param_Angle_Rotation_6_ArtMesh101",
			"GroupId": "ParamGroup48",
			"Name": "[5]头发8_2"
		},
		{
			"Id": "Param_Angle_Rotation_7_ArtMesh101",
			"GroupId": "ParamGroup48",
			"Name": "[6]头发8_2"
		},
		{
			"Id": "Param_Angle_Rotation_1_ArtMesh202",
			"GroupId": "ParamGroup49",
			"Name": "[0]头发8_2阴影透明"
		},
		{
			"Id": "Param_Angle_Rotation_2_ArtMesh202",
			"GroupId": "ParamGroup49",
			"Name": "[1]头发8_2阴影透明"
		},
		{
			"Id": "Param_Angle_Rotation_3_ArtMesh202",
			"GroupId": "ParamGroup49",
			"Name": "[2]头发8_2阴影透明"
		},
		{
			"Id": "Param_Angle_Rotation_4_ArtMesh202",
			"GroupId": "ParamGroup49",
			"Name": "[3]头发8_2阴影透明"
		},
		{
			"Id": "Param_Angle_Rotation_5_ArtMesh202",
			"GroupId": "ParamGroup49",
			"Name": "[4]头发8_2阴影透明"
		},
		{
			"Id": "Param_Angle_Rotation_6_ArtMesh202",
			"GroupId": "ParamGroup49",
			"Name": "[5]头发8_2阴影透明"
		},
		{
			"Id": "Param_Angle_Rotation_7_ArtMesh202",
			"GroupId": "ParamGroup49",
			"Name": "[6]头发8_2阴影透明"
		},
		{
			"Id": "Param_Angle_Rotation_1_ArtMesh111",
			"GroupId": "ParamGroup50",
			"Name": "[0]头发8_2阴影"
		},
		{
			"Id": "Param_Angle_Rotation_2_ArtMesh111",
			"GroupId": "ParamGroup50",
			"Name": "[1]头发8_2阴影"
		},
		{
			"Id": "Param_Angle_Rotation_3_ArtMesh111",
			"GroupId": "ParamGroup50",
			"Name": "[2]头发8_2阴影"
		},
		{
			"Id": "Param_Angle_Rotation_4_ArtMesh111",
			"GroupId": "ParamGroup50",
			"Name": "[3]头发8_2阴影"
		},
		{
			"Id": "Param_Angle_Rotation_5_ArtMesh111",
			"GroupId": "ParamGroup50",
			"Name": "[4]头发8_2阴影"
		},
		{
			"Id": "Param_Angle_Rotation_6_ArtMesh111",
			"GroupId": "ParamGroup50",
			"Name": "[5]头发8_2阴影"
		},
		{
			"Id": "Param_Angle_Rotation_7_ArtMesh111",
			"GroupId": "ParamGroup50",
			"Name": "[6]头发8_2阴影"
		},
		{
			"Id": "Param_Angle_Rotation_1_ArtMesh197",
			"GroupId": "ParamGroup51",
			"Name": "[0]头发11_2透明"
		},
		{
			"Id": "Param_Angle_Rotation_2_ArtMesh197",
			"GroupId": "ParamGroup51",
			"Name": "[1]头发11_2透明"
		},
		{
			"Id": "Param_Angle_Rotation_3_ArtMesh197",
			"GroupId": "ParamGroup51",
			"Name": "[2]头发11_2透明"
		},
		{
			"Id": "Param_Angle_Rotation_4_ArtMesh197",
			"GroupId": "ParamGroup51",
			"Name": "[3]头发11_2透明"
		},
		{
			"Id": "Param_Angle_Rotation_5_ArtMesh197",
			"GroupId": "ParamGroup51",
			"Name": "[4]头发11_2透明"
		},
		{
			"Id": "Param_Angle_Rotation_6_ArtMesh197",
			"GroupId": "ParamGroup51",
			"Name": "[5]头发11_2透明"
		},
		{
			"Id": "Param_Angle_Rotation_7_ArtMesh197",
			"GroupId": "ParamGroup51",
			"Name": "[6]头发11_2透明"
		},
		{
			"Id": "Param_Angle_Rotation_1_ArtMesh103",
			"GroupId": "ParamGroup52",
			"Name": "[0]头发11_2"
		},
		{
			"Id": "Param_Angle_Rotation_2_ArtMesh103",
			"GroupId": "ParamGroup52",
			"Name": "[1]头发11_2"
		},
		{
			"Id": "Param_Angle_Rotation_3_ArtMesh103",
			"GroupId": "ParamGroup52",
			"Name": "[2]头发11_2"
		},
		{
			"Id": "Param_Angle_Rotation_4_ArtMesh103",
			"GroupId": "ParamGroup52",
			"Name": "[3]头发11_2"
		},
		{
			"Id": "Param_Angle_Rotation_5_ArtMesh103",
			"GroupId": "ParamGroup52",
			"Name": "[4]头发11_2"
		},
		{
			"Id": "Param_Angle_Rotation_6_ArtMesh103",
			"GroupId": "ParamGroup52",
			"Name": "[5]头发11_2"
		},
		{
			"Id": "Param_Angle_Rotation_7_ArtMesh103",
			"GroupId": "ParamGroup52",
			"Name": "[6]头发11_2"
		},
		{
			"Id": "Param_Angle_Rotation_1_ArtMesh199",
			"GroupId": "ParamGroup53",
			"Name": "[0]头发11_2阴影透明"
		},
		{
			"Id": "Param_Angle_Rotation_2_ArtMesh199",
			"GroupId": "ParamGroup53",
			"Name": "[1]头发11_2阴影透明"
		},
		{
			"Id": "Param_Angle_Rotation_3_ArtMesh199",
			"GroupId": "ParamGroup53",
			"Name": "[2]头发11_2阴影透明"
		},
		{
			"Id": "Param_Angle_Rotation_4_ArtMesh199",
			"GroupId": "ParamGroup53",
			"Name": "[3]头发11_2阴影透明"
		},
		{
			"Id": "Param_Angle_Rotation_5_ArtMesh199",
			"GroupId": "ParamGroup53",
			"Name": "[4]头发11_2阴影透明"
		},
		{
			"Id": "Param_Angle_Rotation_6_ArtMesh199",
			"GroupId": "ParamGroup53",
			"Name": "[5]头发11_2阴影透明"
		},
		{
			"Id": "Param_Angle_Rotation_7_ArtMesh199",
			"GroupId": "ParamGroup53",
			"Name": "[6]头发11_2阴影透明"
		},
		{
			"Id": "Param_Angle_Rotation_1_ArtMesh108",
			"GroupId": "ParamGroup54",
			"Name": "[0]头发11_2阴影"
		},
		{
			"Id": "Param_Angle_Rotation_2_ArtMesh108",
			"GroupId": "ParamGroup54",
			"Name": "[1]头发11_2阴影"
		},
		{
			"Id": "Param_Angle_Rotation_3_ArtMesh108",
			"GroupId": "ParamGroup54",
			"Name": "[2]头发11_2阴影"
		},
		{
			"Id": "Param_Angle_Rotation_4_ArtMesh108",
			"GroupId": "ParamGroup54",
			"Name": "[3]头发11_2阴影"
		},
		{
			"Id": "Param_Angle_Rotation_5_ArtMesh108",
			"GroupId": "ParamGroup54",
			"Name": "[4]头发11_2阴影"
		},
		{
			"Id": "Param_Angle_Rotation_6_ArtMesh108",
			"GroupId": "ParamGroup54",
			"Name": "[5]头发11_2阴影"
		},
		{
			"Id": "Param_Angle_Rotation_7_ArtMesh108",
			"GroupId": "ParamGroup54",
			"Name": "[6]头发11_2阴影"
		},
		{
			"Id": "Param_Angle_Rotation_1_ArtMesh195",
			"GroupId": "ParamGroup55",
			"Name": "[0]头发10_2透明"
		},
		{
			"Id": "Param_Angle_Rotation_2_ArtMesh195",
			"GroupId": "ParamGroup55",
			"Name": "[1]头发10_2透明"
		},
		{
			"Id": "Param_Angle_Rotation_3_ArtMesh195",
			"GroupId": "ParamGroup55",
			"Name": "[2]头发10_2透明"
		},
		{
			"Id": "Param_Angle_Rotation_4_ArtMesh195",
			"GroupId": "ParamGroup55",
			"Name": "[3]头发10_2透明"
		},
		{
			"Id": "Param_Angle_Rotation_5_ArtMesh195",
			"GroupId": "ParamGroup55",
			"Name": "[4]头发10_2透明"
		},
		{
			"Id": "Param_Angle_Rotation_6_ArtMesh195",
			"GroupId": "ParamGroup55",
			"Name": "[5]头发10_2透明"
		},
		{
			"Id": "Param_Angle_Rotation_7_ArtMesh195",
			"GroupId": "ParamGroup55",
			"Name": "[6]头发10_2透明"
		},
		{
			"Id": "Param_Angle_Rotation_8_ArtMesh195",
			"GroupId": "ParamGroup55",
			"Name": "[7]头发10_2透明"
		},
		{
			"Id": "Param_Angle_Rotation_9_ArtMesh195",
			"GroupId": "ParamGroup55",
			"Name": "[8]头发10_2透明"
		},
		{
			"Id": "Param_Angle_Rotation_1_ArtMesh102",
			"GroupId": "ParamGroup56",
			"Name": "[0]头发10_2"
		},
		{
			"Id": "Param_Angle_Rotation_2_ArtMesh102",
			"GroupId": "ParamGroup56",
			"Name": "[1]头发10_2"
		},
		{
			"Id": "Param_Angle_Rotation_3_ArtMesh102",
			"GroupId": "ParamGroup56",
			"Name": "[2]头发10_2"
		},
		{
			"Id": "Param_Angle_Rotation_4_ArtMesh102",
			"GroupId": "ParamGroup56",
			"Name": "[3]头发10_2"
		},
		{
			"Id": "Param_Angle_Rotation_5_ArtMesh102",
			"GroupId": "ParamGroup56",
			"Name": "[4]头发10_2"
		},
		{
			"Id": "Param_Angle_Rotation_6_ArtMesh102",
			"GroupId": "ParamGroup56",
			"Name": "[5]头发10_2"
		},
		{
			"Id": "Param_Angle_Rotation_7_ArtMesh102",
			"GroupId": "ParamGroup56",
			"Name": "[6]头发10_2"
		},
		{
			"Id": "Param_Angle_Rotation_8_ArtMesh102",
			"GroupId": "ParamGroup56",
			"Name": "[7]头发10_2"
		},
		{
			"Id": "Param_Angle_Rotation_9_ArtMesh102",
			"GroupId": "ParamGroup56",
			"Name": "[8]头发10_2"
		},
		{
			"Id": "Param_Angle_Rotation_1_ArtMesh200",
			"GroupId": "ParamGroup57",
			"Name": "[0]头发10_2阴影透明"
		},
		{
			"Id": "Param_Angle_Rotation_2_ArtMesh200",
			"GroupId": "ParamGroup57",
			"Name": "[1]头发10_2阴影透明"
		},
		{
			"Id": "Param_Angle_Rotation_3_ArtMesh200",
			"GroupId": "ParamGroup57",
			"Name": "[2]头发10_2阴影透明"
		},
		{
			"Id": "Param_Angle_Rotation_4_ArtMesh200",
			"GroupId": "ParamGroup57",
			"Name": "[3]头发10_2阴影透明"
		},
		{
			"Id": "Param_Angle_Rotation_5_ArtMesh200",
			"GroupId": "ParamGroup57",
			"Name": "[4]头发10_2阴影透明"
		},
		{
			"Id": "Param_Angle_Rotation_6_ArtMesh200",
			"GroupId": "ParamGroup57",
			"Name": "[5]头发10_2阴影透明"
		},
		{
			"Id": "Param_Angle_Rotation_7_ArtMesh200",
			"GroupId": "ParamGroup57",
			"Name": "[6]头发10_2阴影透明"
		},
		{
			"Id": "Param_Angle_Rotation_8_ArtMesh200",
			"GroupId": "ParamGroup57",
			"Name": "[7]头发10_2阴影透明"
		},
		{
			"Id": "Param_Angle_Rotation_9_ArtMesh200",
			"GroupId": "ParamGroup57",
			"Name": "[8]头发10_2阴影透明"
		},
		{
			"Id": "Param_Angle_Rotation_1_ArtMesh109",
			"GroupId": "ParamGroup58",
			"Name": "[0]头发10_2阴影"
		},
		{
			"Id": "Param_Angle_Rotation_2_ArtMesh109",
			"GroupId": "ParamGroup58",
			"Name": "[1]头发10_2阴影"
		},
		{
			"Id": "Param_Angle_Rotation_3_ArtMesh109",
			"GroupId": "ParamGroup58",
			"Name": "[2]头发10_2阴影"
		},
		{
			"Id": "Param_Angle_Rotation_4_ArtMesh109",
			"GroupId": "ParamGroup58",
			"Name": "[3]头发10_2阴影"
		},
		{
			"Id": "Param_Angle_Rotation_5_ArtMesh109",
			"GroupId": "ParamGroup58",
			"Name": "[4]头发10_2阴影"
		},
		{
			"Id": "Param_Angle_Rotation_6_ArtMesh109",
			"GroupId": "ParamGroup58",
			"Name": "[5]头发10_2阴影"
		},
		{
			"Id": "Param_Angle_Rotation_7_ArtMesh109",
			"GroupId": "ParamGroup58",
			"Name": "[6]头发10_2阴影"
		},
		{
			"Id": "Param_Angle_Rotation_8_ArtMesh109",
			"GroupId": "ParamGroup58",
			"Name": "[7]头发10_2阴影"
		},
		{
			"Id": "Param_Angle_Rotation_9_ArtMesh109",
			"GroupId": "ParamGroup58",
			"Name": "[8]头发10_2阴影"
		},
		{
			"Id": "Param_Angle_Rotation_1_ArtMesh196",
			"GroupId": "ParamGroup59",
			"Name": "[0]头发1_3透明"
		},
		{
			"Id": "Param_Angle_Rotation_2_ArtMesh196",
			"GroupId": "ParamGroup59",
			"Name": "[1]头发1_3透明"
		},
		{
			"Id": "Param_Angle_Rotation_3_ArtMesh196",
			"GroupId": "ParamGroup59",
			"Name": "[2]头发1_3透明"
		},
		{
			"Id": "Param_Angle_Rotation_4_ArtMesh196",
			"GroupId": "ParamGroup59",
			"Name": "[3]头发1_3透明"
		},
		{
			"Id": "Param_Angle_Rotation_5_ArtMesh196",
			"GroupId": "ParamGroup59",
			"Name": "[4]头发1_3透明"
		},
		{
			"Id": "Param_Angle_Rotation_6_ArtMesh196",
			"GroupId": "ParamGroup59",
			"Name": "[5]头发1_3透明"
		},
		{
			"Id": "Param_Angle_Rotation_7_ArtMesh196",
			"GroupId": "ParamGroup59",
			"Name": "[6]头发1_3透明"
		},
		{
			"Id": "Param_Angle_Rotation_8_ArtMesh196",
			"GroupId": "ParamGroup59",
			"Name": "[7]头发1_3透明"
		},
		{
			"Id": "Param_Angle_Rotation_9_ArtMesh196",
			"GroupId": "ParamGroup59",
			"Name": "[8]头发1_3透明"
		},
		{
			"Id": "Param_Angle_Rotation_1_ArtMesh104",
			"GroupId": "ParamGroup60",
			"Name": "[0]头发1_3"
		},
		{
			"Id": "Param_Angle_Rotation_2_ArtMesh104",
			"GroupId": "ParamGroup60",
			"Name": "[1]头发1_3"
		},
		{
			"Id": "Param_Angle_Rotation_3_ArtMesh104",
			"GroupId": "ParamGroup60",
			"Name": "[2]头发1_3"
		},
		{
			"Id": "Param_Angle_Rotation_4_ArtMesh104",
			"GroupId": "ParamGroup60",
			"Name": "[3]头发1_3"
		},
		{
			"Id": "Param_Angle_Rotation_5_ArtMesh104",
			"GroupId": "ParamGroup60",
			"Name": "[4]头发1_3"
		},
		{
			"Id": "Param_Angle_Rotation_6_ArtMesh104",
			"GroupId": "ParamGroup60",
			"Name": "[5]头发1_3"
		},
		{
			"Id": "Param_Angle_Rotation_7_ArtMesh104",
			"GroupId": "ParamGroup60",
			"Name": "[6]头发1_3"
		},
		{
			"Id": "Param_Angle_Rotation_8_ArtMesh104",
			"GroupId": "ParamGroup60",
			"Name": "[7]头发1_3"
		},
		{
			"Id": "Param_Angle_Rotation_9_ArtMesh104",
			"GroupId": "ParamGroup60",
			"Name": "[8]头发1_3"
		},
		{
			"Id": "Param_Angle_Rotation_1_ArtMesh105",
			"GroupId": "ParamGroup61",
			"Name": "[0]头发2_3"
		},
		{
			"Id": "Param_Angle_Rotation_2_ArtMesh105",
			"GroupId": "ParamGroup61",
			"Name": "[1]头发2_3"
		},
		{
			"Id": "Param_Angle_Rotation_3_ArtMesh105",
			"GroupId": "ParamGroup61",
			"Name": "[2]头发2_3"
		},
		{
			"Id": "Param_Angle_Rotation_4_ArtMesh105",
			"GroupId": "ParamGroup61",
			"Name": "[3]头发2_3"
		},
		{
			"Id": "Param_Angle_Rotation_5_ArtMesh105",
			"GroupId": "ParamGroup61",
			"Name": "[4]头发2_3"
		},
		{
			"Id": "Param_Angle_Rotation_6_ArtMesh105",
			"GroupId": "ParamGroup61",
			"Name": "[5]头发2_3"
		},
		{
			"Id": "Param_Angle_Rotation_7_ArtMesh105",
			"GroupId": "ParamGroup61",
			"Name": "[6]头发2_3"
		},
		{
			"Id": "Param_Angle_Rotation_8_ArtMesh105",
			"GroupId": "ParamGroup61",
			"Name": "[7]头发2_3"
		},
		{
			"Id": "Param_Angle_Rotation_9_ArtMesh105",
			"GroupId": "ParamGroup61",
			"Name": "[8]头发2_3"
		},
		{
			"Id": "Param_Angle_Rotation_1_ArtMesh106",
			"GroupId": "ParamGroup62",
			"Name": "[0]头发3_3"
		},
		{
			"Id": "Param_Angle_Rotation_2_ArtMesh106",
			"GroupId": "ParamGroup62",
			"Name": "[1]头发3_3"
		},
		{
			"Id": "Param_Angle_Rotation_3_ArtMesh106",
			"GroupId": "ParamGroup62",
			"Name": "[2]头发3_3"
		},
		{
			"Id": "Param_Angle_Rotation_4_ArtMesh106",
			"GroupId": "ParamGroup62",
			"Name": "[3]头发3_3"
		},
		{
			"Id": "Param_Angle_Rotation_5_ArtMesh106",
			"GroupId": "ParamGroup62",
			"Name": "[4]头发3_3"
		},
		{
			"Id": "Param_Angle_Rotation_6_ArtMesh106",
			"GroupId": "ParamGroup62",
			"Name": "[5]头发3_3"
		},
		{
			"Id": "Param_Angle_Rotation_7_ArtMesh106",
			"GroupId": "ParamGroup62",
			"Name": "[6]头发3_3"
		},
		{
			"Id": "Param_Angle_Rotation_8_ArtMesh106",
			"GroupId": "ParamGroup62",
			"Name": "[7]头发3_3"
		},
		{
			"Id": "Param_Angle_Rotation_9_ArtMesh106",
			"GroupId": "ParamGroup62",
			"Name": "[8]头发3_3"
		},
		{
			"Id": "Param_Angle_Rotation_1_ArtMesh120",
			"GroupId": "ParamGroup63",
			"Name": "[0]头发4_4"
		},
		{
			"Id": "Param_Angle_Rotation_2_ArtMesh120",
			"GroupId": "ParamGroup63",
			"Name": "[1]头发4_4"
		},
		{
			"Id": "Param_Angle_Rotation_3_ArtMesh120",
			"GroupId": "ParamGroup63",
			"Name": "[2]头发4_4"
		},
		{
			"Id": "Param_Angle_Rotation_4_ArtMesh120",
			"GroupId": "ParamGroup63",
			"Name": "[3]头发4_4"
		},
		{
			"Id": "Param_Angle_Rotation_5_ArtMesh120",
			"GroupId": "ParamGroup63",
			"Name": "[4]头发4_4"
		},
		{
			"Id": "Param_Angle_Rotation_1_ArtMesh117",
			"GroupId": "ParamGroup64",
			"Name": "[0]头发1_4"
		},
		{
			"Id": "Param_Angle_Rotation_2_ArtMesh117",
			"GroupId": "ParamGroup64",
			"Name": "[1]头发1_4"
		},
		{
			"Id": "Param_Angle_Rotation_3_ArtMesh117",
			"GroupId": "ParamGroup64",
			"Name": "[2]头发1_4"
		},
		{
			"Id": "Param_Angle_Rotation_4_ArtMesh117",
			"GroupId": "ParamGroup64",
			"Name": "[3]头发1_4"
		},
		{
			"Id": "Param_Angle_Rotation_5_ArtMesh117",
			"GroupId": "ParamGroup64",
			"Name": "[4]头发1_4"
		},
		{
			"Id": "Param_Angle_Rotation_1_ArtMesh118",
			"GroupId": "ParamGroup65",
			"Name": "[0]头发2_4"
		},
		{
			"Id": "Param_Angle_Rotation_2_ArtMesh118",
			"GroupId": "ParamGroup65",
			"Name": "[1]头发2_4"
		},
		{
			"Id": "Param_Angle_Rotation_3_ArtMesh118",
			"GroupId": "ParamGroup65",
			"Name": "[2]头发2_4"
		},
		{
			"Id": "Param_Angle_Rotation_4_ArtMesh118",
			"GroupId": "ParamGroup65",
			"Name": "[3]头发2_4"
		},
		{
			"Id": "Param_Angle_Rotation_5_ArtMesh118",
			"GroupId": "ParamGroup65",
			"Name": "[4]头发2_4"
		},
		{
			"Id": "Param_Angle_Rotation_6_ArtMesh118",
			"GroupId": "ParamGroup65",
			"Name": "[5]头发2_4"
		},
		{
			"Id": "Param_Angle_Rotation_7_ArtMesh118",
			"GroupId": "ParamGroup65",
			"Name": "[6]头发2_4"
		},
		{
			"Id": "Param_Angle_Rotation_8_ArtMesh118",
			"GroupId": "ParamGroup65",
			"Name": "[7]头发2_4"
		},
		{
			"Id": "Param_Angle_Rotation_9_ArtMesh118",
			"GroupId": "ParamGroup65",
			"Name": "[8]头发2_4"
		},
		{
			"Id": "Param_Angle_Rotation_1_ArtMesh119",
			"GroupId": "ParamGroup66",
			"Name": "[0]头发3_4"
		},
		{
			"Id": "Param_Angle_Rotation_2_ArtMesh119",
			"GroupId": "ParamGroup66",
			"Name": "[1]头发3_4"
		},
		{
			"Id": "Param_Angle_Rotation_3_ArtMesh119",
			"GroupId": "ParamGroup66",
			"Name": "[2]头发3_4"
		},
		{
			"Id": "Param_Angle_Rotation_4_ArtMesh119",
			"GroupId": "ParamGroup66",
			"Name": "[3]头发3_4"
		},
		{
			"Id": "Param_Angle_Rotation_5_ArtMesh119",
			"GroupId": "ParamGroup66",
			"Name": "[4]头发3_4"
		},
		{
			"Id": "Param_Angle_Rotation_6_ArtMesh119",
			"GroupId": "ParamGroup66",
			"Name": "[5]头发3_4"
		},
		{
			"Id": "Param_Angle_Rotation_7_ArtMesh119",
			"GroupId": "ParamGroup66",
			"Name": "[6]头发3_4"
		},
		{
			"Id": "Param_Angle_Rotation_8_ArtMesh119",
			"GroupId": "ParamGroup66",
			"Name": "[7]头发3_4"
		},
		{
			"Id": "Param_Angle_Rotation_9_ArtMesh119",
			"GroupId": "ParamGroup66",
			"Name": "[8]头发3_4"
		},
		{
			"Id": "Param_Angle_Rotation_1_ArtMesh5",
			"GroupId": "ParamGroup67",
			"Name": "[0]发饰蝴蝶结黑_1"
		},
		{
			"Id": "Param_Angle_Rotation_2_ArtMesh5",
			"GroupId": "ParamGroup67",
			"Name": "[1]发饰蝴蝶结黑_1"
		},
		{
			"Id": "Param_Angle_Rotation_3_ArtMesh5",
			"GroupId": "ParamGroup67",
			"Name": "[2]发饰蝴蝶结黑_1"
		},
		{
			"Id": "Param_Angle_Rotation_4_ArtMesh5",
			"GroupId": "ParamGroup67",
			"Name": "[3]发饰蝴蝶结黑_1"
		},
		{
			"Id": "Param_Angle_Rotation_5_ArtMesh5",
			"GroupId": "ParamGroup67",
			"Name": "[4]发饰蝴蝶结黑_1"
		},
		{
			"Id": "Param_Angle_Rotation_6_ArtMesh5",
			"GroupId": "ParamGroup67",
			"Name": "[5]发饰蝴蝶结黑_1"
		},
		{
			"Id": "Param_Angle_Rotation_7_ArtMesh5",
			"GroupId": "ParamGroup67",
			"Name": "[6]发饰蝴蝶结黑_1"
		},
		{
			"Id": "Param_Angle_Rotation_1_ArtMesh12",
			"GroupId": "ParamGroup68",
			"Name": "[0]发饰蝴蝶结黑_1阴影"
		},
		{
			"Id": "Param_Angle_Rotation_2_ArtMesh12",
			"GroupId": "ParamGroup68",
			"Name": "[1]发饰蝴蝶结黑_1阴影"
		},
		{
			"Id": "Param_Angle_Rotation_3_ArtMesh12",
			"GroupId": "ParamGroup68",
			"Name": "[2]发饰蝴蝶结黑_1阴影"
		},
		{
			"Id": "Param_Angle_Rotation_4_ArtMesh12",
			"GroupId": "ParamGroup68",
			"Name": "[3]发饰蝴蝶结黑_1阴影"
		},
		{
			"Id": "Param_Angle_Rotation_5_ArtMesh12",
			"GroupId": "ParamGroup68",
			"Name": "[4]发饰蝴蝶结黑_1阴影"
		},
		{
			"Id": "Param_Angle_Rotation_6_ArtMesh12",
			"GroupId": "ParamGroup68",
			"Name": "[5]发饰蝴蝶结黑_1阴影"
		},
		{
			"Id": "Param_Angle_Rotation_7_ArtMesh12",
			"GroupId": "ParamGroup68",
			"Name": "[6]发饰蝴蝶结黑_1阴影"
		},
		{
			"Id": "Param_Angle_Rotation_1_ArtMesh6",
			"GroupId": "ParamGroup69",
			"Name": "[0]发饰蝴蝶结黑_2"
		},
		{
			"Id": "Param_Angle_Rotation_2_ArtMesh6",
			"GroupId": "ParamGroup69",
			"Name": "[1]发饰蝴蝶结黑_2"
		},
		{
			"Id": "Param_Angle_Rotation_3_ArtMesh6",
			"GroupId": "ParamGroup69",
			"Name": "[2]发饰蝴蝶结黑_2"
		},
		{
			"Id": "Param_Angle_Rotation_4_ArtMesh6",
			"GroupId": "ParamGroup69",
			"Name": "[3]发饰蝴蝶结黑_2"
		},
		{
			"Id": "Param_Angle_Rotation_5_ArtMesh6",
			"GroupId": "ParamGroup69",
			"Name": "[4]发饰蝴蝶结黑_2"
		},
		{
			"Id": "Param_Angle_Rotation_1_ArtMesh11",
			"GroupId": "ParamGroup70",
			"Name": "[0]发饰蝴蝶结黑_2 阴影"
		},
		{
			"Id": "Param_Angle_Rotation_2_ArtMesh11",
			"GroupId": "ParamGroup70",
			"Name": "[1]发饰蝴蝶结黑_2 阴影"
		},
		{
			"Id": "Param_Angle_Rotation_3_ArtMesh11",
			"GroupId": "ParamGroup70",
			"Name": "[2]发饰蝴蝶结黑_2 阴影"
		},
		{
			"Id": "Param_Angle_Rotation_4_ArtMesh11",
			"GroupId": "ParamGroup70",
			"Name": "[3]发饰蝴蝶结黑_2 阴影"
		},
		{
			"Id": "Param_Angle_Rotation_5_ArtMesh11",
			"GroupId": "ParamGroup70",
			"Name": "[4]发饰蝴蝶结黑_2 阴影"
		},
		{
			"Id": "Param_Angle_Rotation_1_ArtMesh7",
			"GroupId": "ParamGroup71",
			"Name": "[0]发饰蝴蝶结黑_3"
		},
		{
			"Id": "Param_Angle_Rotation_2_ArtMesh7",
			"GroupId": "ParamGroup71",
			"Name": "[1]发饰蝴蝶结黑_3"
		},
		{
			"Id": "Param_Angle_Rotation_3_ArtMesh7",
			"GroupId": "ParamGroup71",
			"Name": "[2]发饰蝴蝶结黑_3"
		},
		{
			"Id": "Param_Angle_Rotation_4_ArtMesh7",
			"GroupId": "ParamGroup71",
			"Name": "[3]发饰蝴蝶结黑_3"
		},
		{
			"Id": "Param_Angle_Rotation_5_ArtMesh7",
			"GroupId": "ParamGroup71",
			"Name": "[4]发饰蝴蝶结黑_3"
		},
		{
			"Id": "Param_Angle_Rotation_6_ArtMesh7",
			"GroupId": "ParamGroup71",
			"Name": "[5]发饰蝴蝶结黑_3"
		},
		{
			"Id": "Param_Angle_Rotation_7_ArtMesh7",
			"GroupId": "ParamGroup71",
			"Name": "[6]发饰蝴蝶结黑_3"
		},
		{
			"Id": "Param_Angle_Rotation_8_ArtMesh7",
			"GroupId": "ParamGroup71",
			"Name": "[7]发饰蝴蝶结黑_3"
		},
		{
			"Id": "Param_Angle_Rotation_9_ArtMesh7",
			"GroupId": "ParamGroup71",
			"Name": "[8]发饰蝴蝶结黑_3"
		},
		{
			"Id": "Param_Angle_Rotation_1_ArtMesh10",
			"GroupId": "ParamGroup72",
			"Name": "[0]发饰蝴蝶结黑_3阴影"
		},
		{
			"Id": "Param_Angle_Rotation_2_ArtMesh10",
			"GroupId": "ParamGroup72",
			"Name": "[1]发饰蝴蝶结黑_3阴影"
		},
		{
			"Id": "Param_Angle_Rotation_3_ArtMesh10",
			"GroupId": "ParamGroup72",
			"Name": "[2]发饰蝴蝶结黑_3阴影"
		},
		{
			"Id": "Param_Angle_Rotation_4_ArtMesh10",
			"GroupId": "ParamGroup72",
			"Name": "[3]发饰蝴蝶结黑_3阴影"
		},
		{
			"Id": "Param_Angle_Rotation_5_ArtMesh10",
			"GroupId": "ParamGroup72",
			"Name": "[4]发饰蝴蝶结黑_3阴影"
		},
		{
			"Id": "Param_Angle_Rotation_6_ArtMesh10",
			"GroupId": "ParamGroup72",
			"Name": "[5]发饰蝴蝶结黑_3阴影"
		},
		{
			"Id": "Param_Angle_Rotation_7_ArtMesh10",
			"GroupId": "ParamGroup72",
			"Name": "[6]发饰蝴蝶结黑_3阴影"
		},
		{
			"Id": "Param_Angle_Rotation_8_ArtMesh10",
			"GroupId": "ParamGroup72",
			"Name": "[7]发饰蝴蝶结黑_3阴影"
		},
		{
			"Id": "Param_Angle_Rotation_9_ArtMesh10",
			"GroupId": "ParamGroup72",
			"Name": "[8]发饰蝴蝶结黑_3阴影"
		},
		{
			"Id": "Param_Angle_Rotation_1_ArtMesh8",
			"GroupId": "ParamGroup73",
			"Name": "[0]发饰蝴蝶结黑_4"
		},
		{
			"Id": "Param_Angle_Rotation_2_ArtMesh8",
			"GroupId": "ParamGroup73",
			"Name": "[1]发饰蝴蝶结黑_4"
		},
		{
			"Id": "Param_Angle_Rotation_3_ArtMesh8",
			"GroupId": "ParamGroup73",
			"Name": "[2]发饰蝴蝶结黑_4"
		},
		{
			"Id": "Param_Angle_Rotation_4_ArtMesh8",
			"GroupId": "ParamGroup73",
			"Name": "[3]发饰蝴蝶结黑_4"
		},
		{
			"Id": "Param_Angle_Rotation_5_ArtMesh8",
			"GroupId": "ParamGroup73",
			"Name": "[4]发饰蝴蝶结黑_4"
		},
		{
			"Id": "Param_Angle_Rotation_6_ArtMesh8",
			"GroupId": "ParamGroup73",
			"Name": "[5]发饰蝴蝶结黑_4"
		},
		{
			"Id": "Param_Angle_Rotation_7_ArtMesh8",
			"GroupId": "ParamGroup73",
			"Name": "[6]发饰蝴蝶结黑_4"
		},
		{
			"Id": "Param_Angle_Rotation_8_ArtMesh8",
			"GroupId": "ParamGroup73",
			"Name": "[7]发饰蝴蝶结黑_4"
		},
		{
			"Id": "Param_Angle_Rotation_9_ArtMesh8",
			"GroupId": "ParamGroup73",
			"Name": "[8]发饰蝴蝶结黑_4"
		},
		{
			"Id": "Param_Angle_Rotation_1_ArtMesh9",
			"GroupId": "ParamGroup74",
			"Name": "[0]发饰蝴蝶结黑_4阴影"
		},
		{
			"Id": "Param_Angle_Rotation_2_ArtMesh9",
			"GroupId": "ParamGroup74",
			"Name": "[1]发饰蝴蝶结黑_4阴影"
		},
		{
			"Id": "Param_Angle_Rotation_3_ArtMesh9",
			"GroupId": "ParamGroup74",
			"Name": "[2]发饰蝴蝶结黑_4阴影"
		},
		{
			"Id": "Param_Angle_Rotation_4_ArtMesh9",
			"GroupId": "ParamGroup74",
			"Name": "[3]发饰蝴蝶结黑_4阴影"
		},
		{
			"Id": "Param_Angle_Rotation_5_ArtMesh9",
			"GroupId": "ParamGroup74",
			"Name": "[4]发饰蝴蝶结黑_4阴影"
		},
		{
			"Id": "Param_Angle_Rotation_6_ArtMesh9",
			"GroupId": "ParamGroup74",
			"Name": "[5]发饰蝴蝶结黑_4阴影"
		},
		{
			"Id": "Param_Angle_Rotation_7_ArtMesh9",
			"GroupId": "ParamGroup74",
			"Name": "[6]发饰蝴蝶结黑_4阴影"
		},
		{
			"Id": "Param_Angle_Rotation_8_ArtMesh9",
			"GroupId": "ParamGroup74",
			"Name": "[7]发饰蝴蝶结黑_4阴影"
		},
		{
			"Id": "Param_Angle_Rotation_9_ArtMesh9",
			"GroupId": "ParamGroup74",
			"Name": "[8]发饰蝴蝶结黑_4阴影"
		},
		{
			"Id": "Param_Angle_Rotation_1_ArtMesh13",
			"GroupId": "ParamGroup75",
			"Name": "[0]发饰蝴蝶结蓝_1"
		},
		{
			"Id": "Param_Angle_Rotation_2_ArtMesh13",
			"GroupId": "ParamGroup75",
			"Name": "[1]发饰蝴蝶结蓝_1"
		},
		{
			"Id": "Param_Angle_Rotation_3_ArtMesh13",
			"GroupId": "ParamGroup75",
			"Name": "[2]发饰蝴蝶结蓝_1"
		},
		{
			"Id": "Param_Angle_Rotation_4_ArtMesh13",
			"GroupId": "ParamGroup75",
			"Name": "[3]发饰蝴蝶结蓝_1"
		},
		{
			"Id": "Param_Angle_Rotation_5_ArtMesh13",
			"GroupId": "ParamGroup75",
			"Name": "[4]发饰蝴蝶结蓝_1"
		},
		{
			"Id": "Param_Angle_Rotation_6_ArtMesh13",
			"GroupId": "ParamGroup75",
			"Name": "[5]发饰蝴蝶结蓝_1"
		},
		{
			"Id": "Param_Angle_Rotation_7_ArtMesh13",
			"GroupId": "ParamGroup75",
			"Name": "[6]发饰蝴蝶结蓝_1"
		},
		{
			"Id": "Param_Angle_Rotation_1_ArtMesh14",
			"GroupId": "ParamGroup76",
			"Name": "[0]发饰蝴蝶结蓝_2"
		},
		{
			"Id": "Param_Angle_Rotation_2_ArtMesh14",
			"GroupId": "ParamGroup76",
			"Name": "[1]发饰蝴蝶结蓝_2"
		},
		{
			"Id": "Param_Angle_Rotation_3_ArtMesh14",
			"GroupId": "ParamGroup76",
			"Name": "[2]发饰蝴蝶结蓝_2"
		},
		{
			"Id": "Param_Angle_Rotation_4_ArtMesh14",
			"GroupId": "ParamGroup76",
			"Name": "[3]发饰蝴蝶结蓝_2"
		},
		{
			"Id": "Param_Angle_Rotation_5_ArtMesh14",
			"GroupId": "ParamGroup76",
			"Name": "[4]发饰蝴蝶结蓝_2"
		},
		{
			"Id": "Param_Angle_Rotation_6_ArtMesh14",
			"GroupId": "ParamGroup76",
			"Name": "[5]发饰蝴蝶结蓝_2"
		},
		{
			"Id": "Param_Angle_Rotation_7_ArtMesh14",
			"GroupId": "ParamGroup76",
			"Name": "[6]发饰蝴蝶结蓝_2"
		},
		{
			"Id": "Param_Angle_Rotation_1_ArtMesh18",
			"GroupId": "ParamGroup77",
			"Name": "[0]发饰蝴蝶结蓝_2阴影"
		},
		{
			"Id": "Param_Angle_Rotation_2_ArtMesh18",
			"GroupId": "ParamGroup77",
			"Name": "[1]发饰蝴蝶结蓝_2阴影"
		},
		{
			"Id": "Param_Angle_Rotation_3_ArtMesh18",
			"GroupId": "ParamGroup77",
			"Name": "[2]发饰蝴蝶结蓝_2阴影"
		},
		{
			"Id": "Param_Angle_Rotation_4_ArtMesh18",
			"GroupId": "ParamGroup77",
			"Name": "[3]发饰蝴蝶结蓝_2阴影"
		},
		{
			"Id": "Param_Angle_Rotation_5_ArtMesh18",
			"GroupId": "ParamGroup77",
			"Name": "[4]发饰蝴蝶结蓝_2阴影"
		},
		{
			"Id": "Param_Angle_Rotation_6_ArtMesh18",
			"GroupId": "ParamGroup77",
			"Name": "[5]发饰蝴蝶结蓝_2阴影"
		},
		{
			"Id": "Param_Angle_Rotation_7_ArtMesh18",
			"GroupId": "ParamGroup77",
			"Name": "[6]发饰蝴蝶结蓝_2阴影"
		},
		{
			"Id": "Param_Angle_Rotation_1_ArtMesh15",
			"GroupId": "ParamGroup78",
			"Name": "[0]发饰蝴蝶结蓝_3"
		},
		{
			"Id": "Param_Angle_Rotation_2_ArtMesh15",
			"GroupId": "ParamGroup78",
			"Name": "[1]发饰蝴蝶结蓝_3"
		},
		{
			"Id": "Param_Angle_Rotation_3_ArtMesh15",
			"GroupId": "ParamGroup78",
			"Name": "[2]发饰蝴蝶结蓝_3"
		},
		{
			"Id": "Param_Angle_Rotation_4_ArtMesh15",
			"GroupId": "ParamGroup78",
			"Name": "[3]发饰蝴蝶结蓝_3"
		},
		{
			"Id": "Param_Angle_Rotation_5_ArtMesh15",
			"GroupId": "ParamGroup78",
			"Name": "[4]发饰蝴蝶结蓝_3"
		},
		{
			"Id": "Param_Angle_Rotation_1_ArtMesh19",
			"GroupId": "ParamGroup79",
			"Name": "[0]发饰蝴蝶结蓝_3阴影"
		},
		{
			"Id": "Param_Angle_Rotation_2_ArtMesh19",
			"GroupId": "ParamGroup79",
			"Name": "[1]发饰蝴蝶结蓝_3阴影"
		},
		{
			"Id": "Param_Angle_Rotation_3_ArtMesh19",
			"GroupId": "ParamGroup79",
			"Name": "[2]发饰蝴蝶结蓝_3阴影"
		},
		{
			"Id": "Param_Angle_Rotation_4_ArtMesh19",
			"GroupId": "ParamGroup79",
			"Name": "[3]发饰蝴蝶结蓝_3阴影"
		},
		{
			"Id": "Param_Angle_Rotation_5_ArtMesh19",
			"GroupId": "ParamGroup79",
			"Name": "[4]发饰蝴蝶结蓝_3阴影"
		},
		{
			"Id": "Param_Angle_Rotation_1_ArtMesh16",
			"GroupId": "ParamGroup80",
			"Name": "[0]发饰蝴蝶结蓝_4"
		},
		{
			"Id": "Param_Angle_Rotation_2_ArtMesh16",
			"GroupId": "ParamGroup80",
			"Name": "[1]发饰蝴蝶结蓝_4"
		},
		{
			"Id": "Param_Angle_Rotation_3_ArtMesh16",
			"GroupId": "ParamGroup80",
			"Name": "[2]发饰蝴蝶结蓝_4"
		},
		{
			"Id": "Param_Angle_Rotation_4_ArtMesh16",
			"GroupId": "ParamGroup80",
			"Name": "[3]发饰蝴蝶结蓝_4"
		},
		{
			"Id": "Param_Angle_Rotation_5_ArtMesh16",
			"GroupId": "ParamGroup80",
			"Name": "[4]发饰蝴蝶结蓝_4"
		},
		{
			"Id": "Param_Angle_Rotation_6_ArtMesh16",
			"GroupId": "ParamGroup80",
			"Name": "[5]发饰蝴蝶结蓝_4"
		},
		{
			"Id": "Param_Angle_Rotation_7_ArtMesh16",
			"GroupId": "ParamGroup80",
			"Name": "[6]发饰蝴蝶结蓝_4"
		},
		{
			"Id": "Param_Angle_Rotation_1_ArtMesh17",
			"GroupId": "ParamGroup81",
			"Name": "[0]发饰蝴蝶结蓝_4阴影"
		},
		{
			"Id": "Param_Angle_Rotation_2_ArtMesh17",
			"GroupId": "ParamGroup81",
			"Name": "[1]发饰蝴蝶结蓝_4阴影"
		},
		{
			"Id": "Param_Angle_Rotation_3_ArtMesh17",
			"GroupId": "ParamGroup81",
			"Name": "[2]发饰蝴蝶结蓝_4阴影"
		},
		{
			"Id": "Param_Angle_Rotation_4_ArtMesh17",
			"GroupId": "ParamGroup81",
			"Name": "[3]发饰蝴蝶结蓝_4阴影"
		},
		{
			"Id": "Param_Angle_Rotation_5_ArtMesh17",
			"GroupId": "ParamGroup81",
			"Name": "[4]发饰蝴蝶结蓝_4阴影"
		},
		{
			"Id": "Param_Angle_Rotation_6_ArtMesh17",
			"GroupId": "ParamGroup81",
			"Name": "[5]发饰蝴蝶结蓝_4阴影"
		},
		{
			"Id": "Param_Angle_Rotation_7_ArtMesh17",
			"GroupId": "ParamGroup81",
			"Name": "[6]发饰蝴蝶结蓝_4阴影"
		},
		{
			"Id": "Param_Angle_Rotation_1_ArtMesh20",
			"GroupId": "ParamGroup82",
			"Name": "[0]发饰蝴蝶结灰_1"
		},
		{
			"Id": "Param_Angle_Rotation_2_ArtMesh20",
			"GroupId": "ParamGroup82",
			"Name": "[1]发饰蝴蝶结灰_1"
		},
		{
			"Id": "Param_Angle_Rotation_3_ArtMesh20",
			"GroupId": "ParamGroup82",
			"Name": "[2]发饰蝴蝶结灰_1"
		},
		{
			"Id": "Param_Angle_Rotation_4_ArtMesh20",
			"GroupId": "ParamGroup82",
			"Name": "[3]发饰蝴蝶结灰_1"
		},
		{
			"Id": "Param_Angle_Rotation_5_ArtMesh20",
			"GroupId": "ParamGroup82",
			"Name": "[4]发饰蝴蝶结灰_1"
		},
		{
			"Id": "Param_Angle_Rotation_6_ArtMesh20",
			"GroupId": "ParamGroup82",
			"Name": "[5]发饰蝴蝶结灰_1"
		},
		{
			"Id": "Param_Angle_Rotation_7_ArtMesh20",
			"GroupId": "ParamGroup82",
			"Name": "[6]发饰蝴蝶结灰_1"
		},
		{
			"Id": "Param_Angle_Rotation_1_ArtMesh24",
			"GroupId": "ParamGroup83",
			"Name": "[0]发饰蝴蝶结灰_1阴影"
		},
		{
			"Id": "Param_Angle_Rotation_2_ArtMesh24",
			"GroupId": "ParamGroup83",
			"Name": "[1]发饰蝴蝶结灰_1阴影"
		},
		{
			"Id": "Param_Angle_Rotation_3_ArtMesh24",
			"GroupId": "ParamGroup83",
			"Name": "[2]发饰蝴蝶结灰_1阴影"
		},
		{
			"Id": "Param_Angle_Rotation_4_ArtMesh24",
			"GroupId": "ParamGroup83",
			"Name": "[3]发饰蝴蝶结灰_1阴影"
		},
		{
			"Id": "Param_Angle_Rotation_5_ArtMesh24",
			"GroupId": "ParamGroup83",
			"Name": "[4]发饰蝴蝶结灰_1阴影"
		},
		{
			"Id": "Param_Angle_Rotation_6_ArtMesh24",
			"GroupId": "ParamGroup83",
			"Name": "[5]发饰蝴蝶结灰_1阴影"
		},
		{
			"Id": "Param_Angle_Rotation_7_ArtMesh24",
			"GroupId": "ParamGroup83",
			"Name": "[6]发饰蝴蝶结灰_1阴影"
		},
		{
			"Id": "Param_Angle_Rotation_1_ArtMesh21",
			"GroupId": "ParamGroup84",
			"Name": "[0]发饰蝴蝶结白_1"
		},
		{
			"Id": "Param_Angle_Rotation_2_ArtMesh21",
			"GroupId": "ParamGroup84",
			"Name": "[1]发饰蝴蝶结白_1"
		},
		{
			"Id": "Param_Angle_Rotation_3_ArtMesh21",
			"GroupId": "ParamGroup84",
			"Name": "[2]发饰蝴蝶结白_1"
		},
		{
			"Id": "Param_Angle_Rotation_4_ArtMesh21",
			"GroupId": "ParamGroup84",
			"Name": "[3]发饰蝴蝶结白_1"
		},
		{
			"Id": "Param_Angle_Rotation_5_ArtMesh21",
			"GroupId": "ParamGroup84",
			"Name": "[4]发饰蝴蝶结白_1"
		},
		{
			"Id": "Param_Angle_Rotation_6_ArtMesh21",
			"GroupId": "ParamGroup84",
			"Name": "[5]发饰蝴蝶结白_1"
		},
		{
			"Id": "Param_Angle_Rotation_7_ArtMesh21",
			"GroupId": "ParamGroup84",
			"Name": "[6]发饰蝴蝶结白_1"
		},
		{
			"Id": "Param_Angle_Rotation_1_ArtMesh23",
			"GroupId": "ParamGroup85",
			"Name": "[0]发饰蝴蝶结白_1阴影"
		},
		{
			"Id": "Param_Angle_Rotation_2_ArtMesh23",
			"GroupId": "ParamGroup85",
			"Name": "[1]发饰蝴蝶结白_1阴影"
		},
		{
			"Id": "Param_Angle_Rotation_3_ArtMesh23",
			"GroupId": "ParamGroup85",
			"Name": "[2]发饰蝴蝶结白_1阴影"
		},
		{
			"Id": "Param_Angle_Rotation_4_ArtMesh23",
			"GroupId": "ParamGroup85",
			"Name": "[3]发饰蝴蝶结白_1阴影"
		},
		{
			"Id": "Param_Angle_Rotation_5_ArtMesh23",
			"GroupId": "ParamGroup85",
			"Name": "[4]发饰蝴蝶结白_1阴影"
		},
		{
			"Id": "Param_Angle_Rotation_6_ArtMesh23",
			"GroupId": "ParamGroup85",
			"Name": "[5]发饰蝴蝶结白_1阴影"
		},
		{
			"Id": "Param_Angle_Rotation_7_ArtMesh23",
			"GroupId": "ParamGroup85",
			"Name": "[6]发饰蝴蝶结白_1阴影"
		},
		{
			"Id": "Param_Angle_Rotation_1_ArtMesh22",
			"GroupId": "ParamGroup86",
			"Name": "[0]发饰蝴蝶结白_2"
		},
		{
			"Id": "Param_Angle_Rotation_2_ArtMesh22",
			"GroupId": "ParamGroup86",
			"Name": "[1]发饰蝴蝶结白_2"
		},
		{
			"Id": "Param_Angle_Rotation_3_ArtMesh22",
			"GroupId": "ParamGroup86",
			"Name": "[2]发饰蝴蝶结白_2"
		},
		{
			"Id": "Param_Angle_Rotation_4_ArtMesh22",
			"GroupId": "ParamGroup86",
			"Name": "[3]发饰蝴蝶结白_2"
		},
		{
			"Id": "Param_Angle_Rotation_5_ArtMesh22",
			"GroupId": "ParamGroup86",
			"Name": "[4]发饰蝴蝶结白_2"
		},
		{
			"Id": "Param_Angle_Rotation_6_ArtMesh22",
			"GroupId": "ParamGroup86",
			"Name": "[5]发饰蝴蝶结白_2"
		},
		{
			"Id": "Param_Angle_Rotation_7_ArtMesh22",
			"GroupId": "ParamGroup86",
			"Name": "[6]发饰蝴蝶结白_2"
		},
		{
			"Id": "Param_Angle_Rotation_1_ArtMesh75",
			"GroupId": "ParamGroup87",
			"Name": "[0]胸饰缎带1"
		},
		{
			"Id": "Param_Angle_Rotation_2_ArtMesh75",
			"GroupId": "ParamGroup87",
			"Name": "[1]胸饰缎带1"
		},
		{
			"Id": "Param_Angle_Rotation_3_ArtMesh75",
			"GroupId": "ParamGroup87",
			"Name": "[2]胸饰缎带1"
		},
		{
			"Id": "Param_Angle_Rotation_4_ArtMesh75",
			"GroupId": "ParamGroup87",
			"Name": "[3]胸饰缎带1"
		},
		{
			"Id": "Param_Angle_Rotation_5_ArtMesh75",
			"GroupId": "ParamGroup87",
			"Name": "[4]胸饰缎带1"
		},
		{
			"Id": "Param_Angle_Rotation_6_ArtMesh75",
			"GroupId": "ParamGroup87",
			"Name": "[5]胸饰缎带1"
		},
		{
			"Id": "Param_Angle_Rotation_7_ArtMesh75",
			"GroupId": "ParamGroup87",
			"Name": "[6]胸饰缎带1"
		},
		{
			"Id": "Param_Angle_Rotation_1_ArtMesh77",
			"GroupId": "ParamGroup88",
			"Name": "[0]胸饰缎带2"
		},
		{
			"Id": "Param_Angle_Rotation_2_ArtMesh77",
			"GroupId": "ParamGroup88",
			"Name": "[1]胸饰缎带2"
		},
		{
			"Id": "Param_Angle_Rotation_3_ArtMesh77",
			"GroupId": "ParamGroup88",
			"Name": "[2]胸饰缎带2"
		},
		{
			"Id": "Param_Angle_Rotation_4_ArtMesh77",
			"GroupId": "ParamGroup88",
			"Name": "[3]胸饰缎带2"
		},
		{
			"Id": "Param_Angle_Rotation_5_ArtMesh77",
			"GroupId": "ParamGroup88",
			"Name": "[4]胸饰缎带2"
		},
		{
			"Id": "Param_Angle_Rotation_6_ArtMesh77",
			"GroupId": "ParamGroup88",
			"Name": "[5]胸饰缎带2"
		},
		{
			"Id": "Param_Angle_Rotation_7_ArtMesh77",
			"GroupId": "ParamGroup88",
			"Name": "[6]胸饰缎带2"
		},
		{
			"Id": "Param_Angle_Rotation_1_ArtMesh76",
			"GroupId": "ParamGroup89",
			"Name": "[0]胸饰缎带1阴影"
		},
		{
			"Id": "Param_Angle_Rotation_2_ArtMesh76",
			"GroupId": "ParamGroup89",
			"Name": "[1]胸饰缎带1阴影"
		},
		{
			"Id": "Param_Angle_Rotation_3_ArtMesh76",
			"GroupId": "ParamGroup89",
			"Name": "[2]胸饰缎带1阴影"
		},
		{
			"Id": "Param_Angle_Rotation_4_ArtMesh76",
			"GroupId": "ParamGroup89",
			"Name": "[3]胸饰缎带1阴影"
		},
		{
			"Id": "Param_Angle_Rotation_5_ArtMesh76",
			"GroupId": "ParamGroup89",
			"Name": "[4]胸饰缎带1阴影"
		},
		{
			"Id": "Param_Angle_Rotation_6_ArtMesh76",
			"GroupId": "ParamGroup89",
			"Name": "[5]胸饰缎带1阴影"
		},
		{
			"Id": "Param_Angle_Rotation_7_ArtMesh76",
			"GroupId": "ParamGroup89",
			"Name": "[6]胸饰缎带1阴影"
		},
		{
			"Id": "Param_Angle_Rotation_1_ArtMesh78",
			"GroupId": "ParamGroup90",
			"Name": "[0]胸饰缎带2阴影"
		},
		{
			"Id": "Param_Angle_Rotation_2_ArtMesh78",
			"GroupId": "ParamGroup90",
			"Name": "[1]胸饰缎带2阴影"
		},
		{
			"Id": "Param_Angle_Rotation_3_ArtMesh78",
			"GroupId": "ParamGroup90",
			"Name": "[2]胸饰缎带2阴影"
		},
		{
			"Id": "Param_Angle_Rotation_4_ArtMesh78",
			"GroupId": "ParamGroup90",
			"Name": "[3]胸饰缎带2阴影"
		},
		{
			"Id": "Param_Angle_Rotation_5_ArtMesh78",
			"GroupId": "ParamGroup90",
			"Name": "[4]胸饰缎带2阴影"
		},
		{
			"Id": "Param_Angle_Rotation_6_ArtMesh78",
			"GroupId": "ParamGroup90",
			"Name": "[5]胸饰缎带2阴影"
		},
		{
			"Id": "Param_Angle_Rotation_7_ArtMesh78",
			"GroupId": "ParamGroup90",
			"Name": "[6]胸饰缎带2阴影"
		}
	],
	"ParameterGroups": [
		{
			"Id": "ParamGroup5",
			"GroupId": "",
			"Name": "脸"
		},
		{
			"Id": "ParamGroup6",
			"GroupId": "",
			"Name": "身体"
		},
		{
			"Id": "ParamGroup",
			"GroupId": "",
			"Name": "眼珠"
		},
		{
			"Id": "ParamGroup2",
			"GroupId": "",
			"Name": "眼睛"
		},
		{
			"Id": "ParamGroup3",
			"GroupId": "",
			"Name": "嘴"
		},
		{
			"Id": "ParamGroup4",
			"GroupId": "",
			"Name": "眉毛"
		},
		{
			"Id": "ParamGroup91",
			"GroupId": "",
			"Name": "手臂"
		},
		{
			"Id": "ParamGroup14",
			"GroupId": "",
			"Name": "摇动"
		},
		{
			"Id": "ParamGroup7",
			"GroupId": "",
			"Name": "蓬松"
		},
		{
			"Id": "ParamGroup8",
			"GroupId": "",
			"Name": "头发1_1"
		},
		{
			"Id": "ParamGroup9",
			"GroupId": "",
			"Name": "头发1_1透明"
		},
		{
			"Id": "ParamGroup10",
			"GroupId": "",
			"Name": "头发1_1 阴影"
		},
		{
			"Id": "ParamGroup11",
			"GroupId": "",
			"Name": "头发2_1"
		},
		{
			"Id": "ParamGroup12",
			"GroupId": "",
			"Name": "头发2_1透明"
		},
		{
			"Id": "ParamGroup13",
			"GroupId": "",
			"Name": "头发2_1阴影"
		},
		{
			"Id": "ParamGroup15",
			"GroupId": "",
			"Name": "发卡透明"
		},
		{
			"Id": "ParamGroup16",
			"GroupId": "",
			"Name": "发卡"
		},
		{
			"Id": "ParamGroup17",
			"GroupId": "",
			"Name": "头发3_2透明"
		},
		{
			"Id": "ParamGroup18",
			"GroupId": "",
			"Name": "头发3_2"
		},
		{
			"Id": "ParamGroup19",
			"GroupId": "",
			"Name": "头发3_2阴影透明"
		},
		{
			"Id": "ParamGroup20",
			"GroupId": "",
			"Name": "头发3_2阴影"
		},
		{
			"Id": "ParamGroup21",
			"GroupId": "",
			"Name": "头发3_1透明"
		},
		{
			"Id": "ParamGroup22",
			"GroupId": "",
			"Name": "头发3_1"
		},
		{
			"Id": "ParamGroup23",
			"GroupId": "",
			"Name": "头发3_1阴影透明"
		},
		{
			"Id": "ParamGroup24",
			"GroupId": "",
			"Name": "头发3_1阴影"
		},
		{
			"Id": "ParamGroup25",
			"GroupId": "",
			"Name": "头发2_2"
		},
		{
			"Id": "ParamGroup26",
			"GroupId": "",
			"Name": "头发1_2"
		},
		{
			"Id": "ParamGroup27",
			"GroupId": "",
			"Name": "头发5_2透明"
		},
		{
			"Id": "ParamGroup28",
			"GroupId": "",
			"Name": "头发5_2"
		},
		{
			"Id": "ParamGroup29",
			"GroupId": "",
			"Name": "头发5_2阴影透明"
		},
		{
			"Id": "ParamGroup30",
			"GroupId": "",
			"Name": "头发5_2阴影"
		},
		{
			"Id": "ParamGroup31",
			"GroupId": "",
			"Name": "头发4_2透明"
		},
		{
			"Id": "ParamGroup32",
			"GroupId": "",
			"Name": "头发4_2"
		},
		{
			"Id": "ParamGroup33",
			"GroupId": "",
			"Name": "头发4_2阴影透明"
		},
		{
			"Id": "ParamGroup34",
			"GroupId": "",
			"Name": "头发4_2阴影"
		},
		{
			"Id": "ParamGroup35",
			"GroupId": "",
			"Name": "头发6_2透明"
		},
		{
			"Id": "ParamGroup36",
			"GroupId": "",
			"Name": "头发6_2"
		},
		{
			"Id": "ParamGroup37",
			"GroupId": "",
			"Name": "头发6_2阴影透明"
		},
		{
			"Id": "ParamGroup38",
			"GroupId": "",
			"Name": "头发6_2阴影"
		},
		{
			"Id": "ParamGroup39",
			"GroupId": "",
			"Name": "头发7_2透明"
		},
		{
			"Id": "ParamGroup40",
			"GroupId": "",
			"Name": "头发7_2"
		},
		{
			"Id": "ParamGroup41",
			"GroupId": "",
			"Name": "头发7_2阴影透明"
		},
		{
			"Id": "ParamGroup42",
			"GroupId": "",
			"Name": "头发7_2阴影"
		},
		{
			"Id": "ParamGroup43",
			"GroupId": "",
			"Name": "头发9_2透明"
		},
		{
			"Id": "ParamGroup44",
			"GroupId": "",
			"Name": "头发9_2"
		},
		{
			"Id": "ParamGroup45",
			"GroupId": "",
			"Name": "头发9_2阴影透明"
		},
		{
			"Id": "ParamGroup46",
			"GroupId": "",
			"Name": "头发9_2阴影"
		},
		{
			"Id": "ParamGroup47",
			"GroupId": "",
			"Name": "头发8_2透明"
		},
		{
			"Id": "ParamGroup48",
			"GroupId": "",
			"Name": "头发8_2"
		},
		{
			"Id": "ParamGroup49",
			"GroupId": "",
			"Name": "头发8_2阴影透明"
		},
		{
			"Id": "ParamGroup50",
			"GroupId": "",
			"Name": "头发8_2阴影"
		},
		{
			"Id": "ParamGroup51",
			"GroupId": "",
			"Name": "头发11_2透明"
		},
		{
			"Id": "ParamGroup52",
			"GroupId": "",
			"Name": "头发11_2"
		},
		{
			"Id": "ParamGroup53",
			"GroupId": "",
			"Name": "头发11_2阴影透明"
		},
		{
			"Id": "ParamGroup54",
			"GroupId": "",
			"Name": "头发11_2阴影"
		},
		{
			"Id": "ParamGroup55",
			"GroupId": "",
			"Name": "头发10_2透明"
		},
		{
			"Id": "ParamGroup56",
			"GroupId": "",
			"Name": "头发10_2"
		},
		{
			"Id": "ParamGroup57",
			"GroupId": "",
			"Name": "头发10_2阴影透明"
		},
		{
			"Id": "ParamGroup58",
			"GroupId": "",
			"Name": "头发10_2阴影"
		},
		{
			"Id": "ParamGroup59",
			"GroupId": "",
			"Name": "头发1_3透明"
		},
		{
			"Id": "ParamGroup60",
			"GroupId": "",
			"Name": "头发1_3"
		},
		{
			"Id": "ParamGroup61",
			"GroupId": "",
			"Name": "头发2_3"
		},
		{
			"Id": "ParamGroup62",
			"GroupId": "",
			"Name": "头发3_3"
		},
		{
			"Id": "ParamGroup63",
			"GroupId": "",
			"Name": "头发4_4"
		},
		{
			"Id": "ParamGroup64",
			"GroupId": "",
			"Name": "头发1_4"
		},
		{
			"Id": "ParamGroup65",
			"GroupId": "",
			"Name": "头发2_4"
		},
		{
			"Id": "ParamGroup66",
			"GroupId": "",
			"Name": "头发3_4"
		},
		{
			"Id": "ParamGroup67",
			"GroupId": "",
			"Name": "发饰蝴蝶结黑_1"
		},
		{
			"Id": "ParamGroup68",
			"GroupId": "",
			"Name": "发饰蝴蝶结黑_1阴影"
		},
		{
			"Id": "ParamGroup69",
			"GroupId": "",
			"Name": "发饰蝴蝶结黑_2"
		},
		{
			"Id": "ParamGroup70",
			"GroupId": "",
			"Name": "发饰蝴蝶结黑_2 阴影"
		},
		{
			"Id": "ParamGroup71",
			"GroupId": "",
			"Name": "发饰蝴蝶结黑_3"
		},
		{
			"Id": "ParamGroup72",
			"GroupId": "",
			"Name": "发饰蝴蝶结黑_3阴影"
		},
		{
			"Id": "ParamGroup73",
			"GroupId": "",
			"Name": "发饰蝴蝶结黑_4"
		},
		{
			"Id": "ParamGroup74",
			"GroupId": "",
			"Name": "发饰蝴蝶结黑_4阴影"
		},
		{
			"Id": "ParamGroup75",
			"GroupId": "",
			"Name": "发饰蝴蝶结蓝_1"
		},
		{
			"Id": "ParamGroup76",
			"GroupId": "",
			"Name": "发饰蝴蝶结蓝_2"
		},
		{
			"Id": "ParamGroup77",
			"GroupId": "",
			"Name": "发饰蝴蝶结蓝_2阴影"
		},
		{
			"Id": "ParamGroup78",
			"GroupId": "",
			"Name": "发饰蝴蝶结蓝_3"
		},
		{
			"Id": "ParamGroup79",
			"GroupId": "",
			"Name": "发饰蝴蝶结蓝_3阴影"
		},
		{
			"Id": "ParamGroup80",
			"GroupId": "",
			"Name": "发饰蝴蝶结蓝_4"
		},
		{
			"Id": "ParamGroup81",
			"GroupId": "",
			"Name": "发饰蝴蝶结蓝_4阴影"
		},
		{
			"Id": "ParamGroup82",
			"GroupId": "",
			"Name": "发饰蝴蝶结灰_1"
		},
		{
			"Id": "ParamGroup83",
			"GroupId": "",
			"Name": "发饰蝴蝶结灰_1阴影"
		},
		{
			"Id": "ParamGroup84",
			"GroupId": "",
			"Name": "发饰蝴蝶结白_1"
		},
		{
			"Id": "ParamGroup85",
			"GroupId": "",
			"Name": "发饰蝴蝶结白_1阴影"
		},
		{
			"Id": "ParamGroup86",
			"GroupId": "",
			"Name": "发饰蝴蝶结白_2"
		},
		{
			"Id": "ParamGroup87",
			"GroupId": "",
			"Name": "胸饰缎带1"
		},
		{
			"Id": "ParamGroup88",
			"GroupId": "",
			"Name": "胸饰缎带2"
		},
		{
			"Id": "ParamGroup89",
			"GroupId": "",
			"Name": "胸饰缎带1阴影"
		},
		{
			"Id": "ParamGroup90",
			"GroupId": "",
			"Name": "胸饰缎带2阴影"
		}
	],
	"Parts": [
		{
			"Id": "Part",
			"Name": "发饰&蝴蝶结"
		},
		{
			"Id": "Part6",
			"Name": "表情替换件"
		},
		{
			"Id": "Part7",
			"Name": "右眉"
		},
		{
			"Id": "Part8",
			"Name": "左眉"
		},
		{
			"Id": "Part9",
			"Name": "右睫毛"
		},
		{
			"Id": "Part10",
			"Name": "左睫毛"
		},
		{
			"Id": "Part13",
			"Name": "右眼内"
		},
		{
			"Id": "Part14",
			"Name": "左眼内"
		},
		{
			"Id": "Part15",
			"Name": "鼻子"
		},
		{
			"Id": "Part16",
			"Name": "唇"
		},
		{
			"Id": "Part17",
			"Name": "胸部饰物"
		},
		{
			"Id": "Part18",
			"Name": "手臂"
		},
		{
			"Id": "Part20",
			"Name": "头发1"
		},
		{
			"Id": "Part21",
			"Name": "头发2"
		},
		{
			"Id": "Part22",
			"Name": "头发3"
		},
		{
			"Id": "Part23",
			"Name": "头发阴影"
		},
		{
			"Id": "Part11",
			"Name": "右下眼皮"
		},
		{
			"Id": "Part12",
			"Name": "左下眼皮"
		},
		{
			"Id": "Part25",
			"Name": "脸"
		},
		{
			"Id": "Part26",
			"Name": "下半身"
		},
		{
			"Id": "Part27",
			"Name": "源"
		},
		{
			"Id": "Part2",
			"Name": "发饰"
		},
		{
			"Id": "Part3",
			"Name": "蝴蝶结黑"
		},
		{
			"Id": "Part4",
			"Name": "蝴蝶结蓝"
		},
		{
			"Id": "Part5",
			"Name": "蝴蝶结灰_白"
		},
		{
			"Id": "ArtMesh75_Skinning",
			"Name": "胸饰缎带1(蒙皮)"
		},
		{
			"Id": "Part105",
			"Name": "胸饰缎带1(旋转)"
		},
		{
			"Id": "ArtMesh76_Skinning",
			"Name": "胸饰缎带1阴影(蒙皮)"
		},
		{
			"Id": "Part107",
			"Name": "胸饰缎带1阴影(旋转)"
		},
		{
			"Id": "ArtMesh77_Skinning",
			"Name": "胸饰缎带2(蒙皮)"
		},
		{
			"Id": "Part106",
			"Name": "胸饰缎带2(旋转)"
		},
		{
			"Id": "ArtMesh78_Skinning",
			"Name": "胸饰缎带2阴影(蒙皮)"
		},
		{
			"Id": "Part108",
			"Name": "胸饰缎带2阴影(旋转)"
		},
		{
			"Id": "ArtMesh187_Skinning",
			"Name": "发卡透明(蒙皮)"
		},
		{
			"Id": "Part33",
			"Name": "发卡透明(旋转)"
		},
		{
			"Id": "ArtMesh184_Skinning",
			"Name": "头发1_1透明(蒙皮)"
		},
		{
			"Id": "Part28",
			"Name": "头发1_1透明(旋转)"
		},
		{
			"Id": "ArtMesh185_Skinning",
			"Name": "头发2_1透明(蒙皮)"
		},
		{
			"Id": "Part31",
			"Name": "头发2_1透明(旋转)"
		},
		{
			"Id": "ArtMesh186_Skinning",
			"Name": "头发3_1透明(蒙皮)"
		},
		{
			"Id": "Part39",
			"Name": "头发3_1透明(旋转)"
		},
		{
			"Id": "ArtMesh87_Skinning",
			"Name": "头发1_1(蒙皮)"
		},
		{
			"Id": "Part19",
			"Name": "头发1_1(旋转)"
		},
		{
			"Id": "ArtMesh149_Skinning",
			"Name": "头发1_1 阴影(蒙皮)"
		},
		{
			"Id": "Part29",
			"Name": "头发1_1 阴影(旋转)"
		},
		{
			"Id": "ArtMesh88_Skinning",
			"Name": "头发2_1(蒙皮)"
		},
		{
			"Id": "Part30",
			"Name": "头发2_1(旋转)"
		},
		{
			"Id": "ArtMesh150_Skinning",
			"Name": "头发2_1阴影(蒙皮)"
		},
		{
			"Id": "Part32",
			"Name": "头发2_1阴影(旋转)"
		},
		{
			"Id": "ArtMesh91_Skinning",
			"Name": "发卡(蒙皮)"
		},
		{
			"Id": "Part34",
			"Name": "发卡(旋转)"
		},
		{
			"Id": "ArtMesh92_Skinning",
			"Name": "头发3_1(蒙皮)"
		},
		{
			"Id": "Part40",
			"Name": "头发3_1(旋转)"
		},
		{
			"Id": "ArtMesh93_Skinning",
			"Name": "头发2_2(蒙皮)"
		},
		{
			"Id": "Part43",
			"Name": "头发2_2(旋转)"
		},
		{
			"Id": "ArtMesh94_Skinning",
			"Name": "头发1_2(蒙皮)"
		},
		{
			"Id": "Part44",
			"Name": "头发1_2(旋转)"
		},
		{
			"Id": "ArtMesh188_Skinning",
			"Name": "头发5_2透明(蒙皮)"
		},
		{
			"Id": "Part45",
			"Name": "头发5_2透明(旋转)"
		},
		{
			"Id": "ArtMesh189_Skinning",
			"Name": "头发4_2透明(蒙皮)"
		},
		{
			"Id": "Part49",
			"Name": "头发4_2透明(旋转)"
		},
		{
			"Id": "ArtMesh190_Skinning",
			"Name": "头发3_2透明(蒙皮)"
		},
		{
			"Id": "Part35",
			"Name": "头发3_2透明(旋转)"
		},
		{
			"Id": "ArtMesh191_Skinning",
			"Name": "头发6_2透明(蒙皮)"
		},
		{
			"Id": "Part53",
			"Name": "头发6_2透明(旋转)"
		},
		{
			"Id": "ArtMesh192_Skinning",
			"Name": "头发7_2透明(蒙皮)"
		},
		{
			"Id": "Part57",
			"Name": "头发7_2透明(旋转)"
		},
		{
			"Id": "ArtMesh193_Skinning",
			"Name": "头发9_2透明(蒙皮)"
		},
		{
			"Id": "Part61",
			"Name": "头发9_2透明(旋转)"
		},
		{
			"Id": "ArtMesh194_Skinning",
			"Name": "头发8_2透明(蒙皮)"
		},
		{
			"Id": "Part65",
			"Name": "头发8_2透明(旋转)"
		},
		{
			"Id": "ArtMesh197_Skinning",
			"Name": "头发11_2透明(蒙皮)"
		},
		{
			"Id": "Part69",
			"Name": "头发11_2透明(旋转)"
		},
		{
			"Id": "ArtMesh195_Skinning",
			"Name": "头发10_2透明(蒙皮)"
		},
		{
			"Id": "Part73",
			"Name": "头发10_2透明(旋转)"
		},
		{
			"Id": "ArtMesh196_Skinning",
			"Name": "头发1_3透明(蒙皮)"
		},
		{
			"Id": "Part77",
			"Name": "头发1_3透明(旋转)"
		},
		{
			"Id": "ArtMesh96_Skinning",
			"Name": "头发5_2(蒙皮)"
		},
		{
			"Id": "Part46",
			"Name": "头发5_2(旋转)"
		},
		{
			"Id": "ArtMesh97_Skinning",
			"Name": "头发4_2(蒙皮)"
		},
		{
			"Id": "Part50",
			"Name": "头发4_2(旋转)"
		},
		{
			"Id": "ArtMesh95_Skinning",
			"Name": "头发3_2(蒙皮)"
		},
		{
			"Id": "Part36",
			"Name": "头发3_2(旋转)"
		},
		{
			"Id": "ArtMesh98_Skinning",
			"Name": "头发6_2(蒙皮)"
		},
		{
			"Id": "Part54",
			"Name": "头发6_2(旋转)"
		},
		{
			"Id": "ArtMesh99_Skinning",
			"Name": "头发7_2(蒙皮)"
		},
		{
			"Id": "Part58",
			"Name": "头发7_2(旋转)"
		},
		{
			"Id": "ArtMesh100_Skinning",
			"Name": "头发9_2(蒙皮)"
		},
		{
			"Id": "Part62",
			"Name": "头发9_2(旋转)"
		},
		{
			"Id": "ArtMesh101_Skinning",
			"Name": "头发8_2(蒙皮)"
		},
		{
			"Id": "Part66",
			"Name": "头发8_2(旋转)"
		},
		{
			"Id": "ArtMesh103_Skinning",
			"Name": "头发11_2(蒙皮)"
		},
		{
			"Id": "Part70",
			"Name": "头发11_2(旋转)"
		},
		{
			"Id": "ArtMesh102_Skinning",
			"Name": "头发10_2(蒙皮)"
		},
		{
			"Id": "Part74",
			"Name": "头发10_2(旋转)"
		},
		{
			"Id": "ArtMesh104_Skinning",
			"Name": "头发1_3(蒙皮)"
		},
		{
			"Id": "Part78",
			"Name": "头发1_3(旋转)"
		},
		{
			"Id": "ArtMesh105_Skinning",
			"Name": "头发2_3(蒙皮)"
		},
		{
			"Id": "Part79",
			"Name": "头发2_3(旋转)"
		},
		{
			"Id": "ArtMesh106_Skinning",
			"Name": "头发3_3(蒙皮)"
		},
		{
			"Id": "Part80",
			"Name": "头发3_3(旋转)"
		},
		{
			"Id": "Part24",
			"Name": "头发阴影"
		},
		{
			"Id": "ArtMesh120_Skinning",
			"Name": "头发4_4(蒙皮)"
		},
		{
			"Id": "Part81",
			"Name": "头发4_4(旋转)"
		},
		{
			"Id": "ArtMesh117_Skinning",
			"Name": "头发1_4(蒙皮)"
		},
		{
			"Id": "Part82",
			"Name": "头发1_4(旋转)"
		},
		{
			"Id": "ArtMesh118_Skinning",
			"Name": "头发2_4(蒙皮)"
		},
		{
			"Id": "Part83",
			"Name": "头发2_4(旋转)"
		},
		{
			"Id": "ArtMesh119_Skinning",
			"Name": "头发3_4(蒙皮)"
		},
		{
			"Id": "Part84",
			"Name": "头发3_4(旋转)"
		},
		{
			"Id": "ArtMesh5_Skinning",
			"Name": "发饰蝴蝶结黑_1(蒙皮)"
		},
		{
			"Id": "Part85",
			"Name": "发饰蝴蝶结黑_1(旋转)"
		},
		{
			"Id": "ArtMesh6_Skinning",
			"Name": "发饰蝴蝶结黑_2(蒙皮)"
		},
		{
			"Id": "Part87",
			"Name": "发饰蝴蝶结黑_2(旋转)"
		},
		{
			"Id": "ArtMesh7_Skinning",
			"Name": "发饰蝴蝶结黑_3(蒙皮)"
		},
		{
			"Id": "Part89",
			"Name": "发饰蝴蝶结黑_3(旋转)"
		},
		{
			"Id": "ArtMesh8_Skinning",
			"Name": "发饰蝴蝶结黑_4(蒙皮)"
		},
		{
			"Id": "Part91",
			"Name": "发饰蝴蝶结黑_4(旋转)"
		},
		{
			"Id": "ArtMesh9_Skinning",
			"Name": "发饰蝴蝶结黑_4阴影(蒙皮)"
		},
		{
			"Id": "Part92",
			"Name": "发饰蝴蝶结黑_4阴影(旋转)"
		},
		{
			"Id": "ArtMesh10_Skinning",
			"Name": "发饰蝴蝶结黑_3阴影(蒙皮)"
		},
		{
			"Id": "Part90",
			"Name": "发饰蝴蝶结黑_3阴影(旋转)"
		},
		{
			"Id": "ArtMesh11_Skinning",
			"Name": "发饰蝴蝶结黑_2 阴影(蒙皮)"
		},
		{
			"Id": "Part88",
			"Name": "发饰蝴蝶结黑_2 阴影(旋转)"
		},
		{
			"Id": "ArtMesh12_Skinning",
			"Name": "发饰蝴蝶结黑_1阴影(蒙皮)"
		},
		{
			"Id": "Part86",
			"Name": "发饰蝴蝶结黑_1阴影(旋转)"
		},
		{
			"Id": "ArtMesh13_Skinning",
			"Name": "发饰蝴蝶结蓝_1(蒙皮)"
		},
		{
			"Id": "Part93",
			"Name": "发饰蝴蝶结蓝_1(旋转)"
		},
		{
			"Id": "ArtMesh14_Skinning",
			"Name": "发饰蝴蝶结蓝_2(蒙皮)"
		},
		{
			"Id": "Part94",
			"Name": "发饰蝴蝶结蓝_2(旋转)"
		},
		{
			"Id": "ArtMesh15_Skinning",
			"Name": "发饰蝴蝶结蓝_3(蒙皮)"
		},
		{
			"Id": "Part96",
			"Name": "发饰蝴蝶结蓝_3(旋转)"
		},
		{
			"Id": "ArtMesh16_Skinning",
			"Name": "发饰蝴蝶结蓝_4(蒙皮)"
		},
		{
			"Id": "Part98",
			"Name": "发饰蝴蝶结蓝_4(旋转)"
		},
		{
			"Id": "ArtMesh17_Skinning",
			"Name": "发饰蝴蝶结蓝_4阴影(蒙皮)"
		},
		{
			"Id": "Part99",
			"Name": "发饰蝴蝶结蓝_4阴影(旋转)"
		},
		{
			"Id": "ArtMesh18_Skinning",
			"Name": "发饰蝴蝶结蓝_2阴影(蒙皮)"
		},
		{
			"Id": "Part95",
			"Name": "发饰蝴蝶结蓝_2阴影(旋转)"
		},
		{
			"Id": "ArtMesh19_Skinning",
			"Name": "发饰蝴蝶结蓝_3阴影(蒙皮)"
		},
		{
			"Id": "Part97",
			"Name": "发饰蝴蝶结蓝_3阴影(旋转)"
		},
		{
			"Id": "ArtMesh20_Skinning",
			"Name": "发饰蝴蝶结灰_1(蒙皮)"
		},
		{
			"Id": "Part100",
			"Name": "发饰蝴蝶结灰_1(旋转)"
		},
		{
			"Id": "ArtMesh21_Skinning",
			"Name": "发饰蝴蝶结白_1(蒙皮)"
		},
		{
			"Id": "Part102",
			"Name": "发饰蝴蝶结白_1(旋转)"
		},
		{
			"Id": "ArtMesh22_Skinning",
			"Name": "发饰蝴蝶结白_2(蒙皮)"
		},
		{
			"Id": "Part104",
			"Name": "发饰蝴蝶结白_2(旋转)"
		},
		{
			"Id": "ArtMesh23_Skinning",
			"Name": "发饰蝴蝶结白_1阴影(蒙皮)"
		},
		{
			"Id": "Part103",
			"Name": "发饰蝴蝶结白_1阴影(旋转)"
		},
		{
			"Id": "ArtMesh24_Skinning",
			"Name": "发饰蝴蝶结灰_1阴影(蒙皮)"
		},
		{
			"Id": "Part101",
			"Name": "发饰蝴蝶结灰_1阴影(旋转)"
		},
		{
			"Id": "ArtMesh198_Skinning",
			"Name": "头发3_1阴影透明(蒙皮)"
		},
		{
			"Id": "Part41",
			"Name": "头发3_1阴影透明(旋转)"
		},
		{
			"Id": "ArtMesh199_Skinning",
			"Name": "头发11_2阴影透明(蒙皮)"
		},
		{
			"Id": "Part71",
			"Name": "头发11_2阴影透明(旋转)"
		},
		{
			"Id": "ArtMesh200_Skinning",
			"Name": "头发10_2阴影透明(蒙皮)"
		},
		{
			"Id": "Part75",
			"Name": "头发10_2阴影透明(旋转)"
		},
		{
			"Id": "ArtMesh201_Skinning",
			"Name": "头发9_2阴影透明(蒙皮)"
		},
		{
			"Id": "Part63",
			"Name": "头发9_2阴影透明(旋转)"
		},
		{
			"Id": "ArtMesh202_Skinning",
			"Name": "头发8_2阴影透明(蒙皮)"
		},
		{
			"Id": "Part67",
			"Name": "头发8_2阴影透明(旋转)"
		},
		{
			"Id": "ArtMesh203_Skinning",
			"Name": "头发7_2阴影透明(蒙皮)"
		},
		{
			"Id": "Part59",
			"Name": "头发7_2阴影透明(旋转)"
		},
		{
			"Id": "ArtMesh204_Skinning",
			"Name": "头发6_2阴影透明(蒙皮)"
		},
		{
			"Id": "Part55",
			"Name": "头发6_2阴影透明(旋转)"
		},
		{
			"Id": "ArtMesh205_Skinning",
			"Name": "头发5_2阴影透明(蒙皮)"
		},
		{
			"Id": "Part47",
			"Name": "头发5_2阴影透明(旋转)"
		},
		{
			"Id": "ArtMesh206_Skinning",
			"Name": "头发4_2阴影透明(蒙皮)"
		},
		{
			"Id": "Part51",
			"Name": "头发4_2阴影透明(旋转)"
		},
		{
			"Id": "ArtMesh207_Skinning",
			"Name": "头发3_2阴影透明(蒙皮)"
		},
		{
			"Id": "Part37",
			"Name": "头发3_2阴影透明(旋转)"
		},
		{
			"Id": "ArtMesh107_Skinning",
			"Name": "头发3_1阴影(蒙皮)"
		},
		{
			"Id": "Part42",
			"Name": "头发3_1阴影(旋转)"
		},
		{
			"Id": "ArtMesh108_Skinning",
			"Name": "头发11_2阴影(蒙皮)"
		},
		{
			"Id": "Part72",
			"Name": "头发11_2阴影(旋转)"
		},
		{
			"Id": "ArtMesh109_Skinning",
			"Name": "头发10_2阴影(蒙皮)"
		},
		{
			"Id": "Part76",
			"Name": "头发10_2阴影(旋转)"
		},
		{
			"Id": "ArtMesh110_Skinning",
			"Name": "头发9_2阴影(蒙皮)"
		},
		{
			"Id": "Part64",
			"Name": "头发9_2阴影(旋转)"
		},
		{
			"Id": "ArtMesh111_Skinning",
			"Name": "头发8_2阴影(蒙皮)"
		},
		{
			"Id": "Part68",
			"Name": "头发8_2阴影(旋转)"
		},
		{
			"Id": "ArtMesh112_Skinning",
			"Name": "头发7_2阴影(蒙皮)"
		},
		{
			"Id": "Part60",
			"Name": "头发7_2阴影(旋转)"
		},
		{
			"Id": "ArtMesh113_Skinning",
			"Name": "头发6_2阴影(蒙皮)"
		},
		{
			"Id": "Part56",
			"Name": "头发6_2阴影(旋转)"
		},
		{
			"Id": "ArtMesh114_Skinning",
			"Name": "头发5_2阴影(蒙皮)"
		},
		{
			"Id": "Part48",
			"Name": "头发5_2阴影(旋转)"
		},
		{
			"Id": "ArtMesh115_Skinning",
			"Name": "头发4_2阴影(蒙皮)"
		},
		{
			"Id": "Part52",
			"Name": "头发4_2阴影(旋转)"
		},
		{
			"Id": "ArtMesh116_Skinning",
			"Name": "头发3_2阴影(蒙皮)"
		},
		{
			"Id": "Part38",
			"Name": "头发3_2阴影(旋转)"
		}
	],
	"CombinedParameters": [
		[
			"ParamAngleX",
			"ParamAngleY"
		]
	]
}